{"CrR":4,"Ps":[{"LN":"Niebrugge","SN":"NIEBRUGGE","Nat":"USA","IsA":false,"ID":"46048","FN":"Jordan"},{"LN":"Gooch","SN":"GOOCH","Nat":"USA","IsA":false,"ID":"46402","FN":"Talor"},{"LN":"Dougherty","SN":"DOUGHERTY","Nat":"USA","IsA":false,"ID":"47663","FN":"Kevin"},{"LN":"Romero","SN":"ROMERO","Nat":"ARG","IsA":false,"ID":"25562","FN":"Andres"},{"LN":"Garnett","SN":"GARNETT","Nat":"USA","IsA":false,"ID":"29535","FN":"Brice"},{"LN":"Poston","SN":"POSTON","Nat":"USA","IsA":false,"ID":"49771","FN":"J.T."},{"LN":"Rai","SN":"RAI","Nat":"ENG","IsA":false,"ID":"46414","FN":"Aaron"},{"LN":"Dunne","SN":"DUNNE","Nat":"IRL","IsA":false,"ID":"46567","FN":"Paul"},{"LN":"Li","SN":"LI","Nat":"CHN","IsA":false,"ID":"35296","FN":"Haotong"},{"LN":"Hagestad","SN":"HAGESTAD","Nat":"USA","IsA":true,"ID":"51586","FN":"Stewart"},{"LN":"Reavie","SN":"REAVIE","Nat":"USA","IsA":false,"ID":"26476","FN":"Chez"},{"LN":"Sauers","SN":"SAUERS","Nat":"USA","IsA":false,"ID":"02049","FN":"Gene"},{"LN":"Snedeker","SN":"SNEDEKER","Nat":"USA","IsA":false,"ID":"27649","FN":"Brandt"},{"LN":"Noren","SN":"NOREN","Nat":"SWE","IsA":false,"ID":"27349","FN":"Alex"},{"LN":"Hatton","SN":"HATTON","Nat":"ENG","IsA":false,"ID":"34363","FN":"Tyrrell"},{"LN":"Pieters","SN":"PIETERS","Nat":"BEL","IsA":false,"ID":"33293","FN":"Thomas"},{"LN":"Koepka","SN":"KOEPKA","Nat":"USA","IsA":false,"ID":"36689","FN":"Brooks"},{"LN":"Woodland","SN":"WOODLAND","Nat":"USA","IsA":false,"ID":"31323","FN":"Gary"},{"LN":"Holmes","SN":"HOLMES","Nat":"USA","IsA":false,"ID":"27141","FN":"J.B."},{"LN":"Gregory","SN":"GREGORY","Nat":"ENG","IsA":true,"ID":"50735","FN":"Scott"},{"LN":"Laird","SN":"LAIRD","Nat":"SCO","IsA":false,"ID":"27936","FN":"Martin"},{"LN":"Kisner","SN":"KISNER","Nat":"USA","IsA":false,"ID":"29478","FN":"Kevin"},{"LN":"Horschel","SN":"HORSCHEL","Nat":"USA","IsA":false,"ID":"29420","FN":"Billy"},{"LN":"Grace","SN":"GRACE","Nat":"RSA","IsA":false,"ID":"29974","FN":"Branden"},{"LN":"Simpson","SN":"SIMPSON","Nat":"USA","IsA":false,"ID":"29221","FN":"Webb"},{"LN":"Els","SN":"ELS","Nat":"RSA","IsA":false,"ID":"06522","FN":"Ernie"},{"LN":"Glover","SN":"GLOVER","Nat":"USA","IsA":false,"ID":"25900","FN":"Lucas"},{"LN":"Alexander","SN":"ALEXANDER","Nat":"USA","IsA":false,"ID":"33408","FN":"Tyson"},{"LN":"Greyserman","SN":"GREYSERMAN","Nat":"USA","IsA":false,"ID":"51977","FN":"Max"},{"LN":"Campbell","SN":"CAMPBELL","Nat":"USA","IsA":false,"ID":"52371","FN":"Matt"},{"LN":"Osborn","SN":"OSBORN","Nat":"USA","IsA":false,"ID":"31559","FN":"Garrett"},{"LN":"Lee","SN":"LEE","Nat":"USA","IsA":true,"ID":"52373","FN":"Walker"},{"LN":"Potter Jr.","SN":"POTTER JR","Nat":"USA","IsA":false,"ID":"27556","FN":"Ted"},{"LN":"Chopra","SN":"CHOPRA","Nat":"SWE","IsA":false,"ID":"20850","FN":"Daniel"},{"LN":"Imahira","SN":"IMAHIRA","Nat":"JPN","IsA":false,"ID":"32775","FN":"Shugo"},{"LN":"Hoffman","SN":"HOFFMAN","Nat":"USA","IsA":false,"ID":"12716","FN":"Charley"},{"LN":"Dufner","SN":"DUFNER","Nat":"USA","IsA":false,"ID":"25686","FN":"Jason"},{"LN":"Tanihara","SN":"TANIHARA","Nat":"JPN","IsA":false,"ID":"21498","FN":"Hideto"},{"LN":"Wang","SN":"WANG","Nat":"KOR","IsA":false,"ID":"39958","FN":"Jeunghun"},{"LN":"Aiken","SN":"AIKEN","Nat":"RSA","IsA":false,"ID":"24461","FN":"Thomas"},{"LN":"Dredge","SN":"DREDGE","Nat":"WAL","IsA":false,"ID":"22983","FN":"Bradley"},{"LN":"Harvey","SN":"HARVEY","Nat":"USA","IsA":true,"ID":"47644","FN":"Scott"},{"LN":"Lovemark","SN":"LOVEMARK","Nat":"USA","IsA":false,"ID":"29461","FN":"Jamie"},{"LN":"Hadwin","SN":"HADWIN","Nat":"CAN","IsA":false,"ID":"33399","FN":"Adam"},{"LN":"Harman","SN":"HARMAN","Nat":"USA","IsA":false,"ID":"27644","FN":"Brian"},{"LN":"Fleetwood","SN":"FLEETWOOD","Nat":"ENG","IsA":false,"ID":"30911","FN":"Tommy"},{"LN":"Cauley","SN":"CAULEY","Nat":"USA","IsA":false,"ID":"34021","FN":"Bud"},{"LN":"Matsuyama","SN":"MATSUYAMA","Nat":"JPN","IsA":false,"ID":"32839","FN":"Hideki"},{"LN":"Fowler","SN":"FOWLER","Nat":"USA","IsA":false,"ID":"32102","FN":"Rickie"},{"LN":"Westwood","SN":"WESTWOOD","Nat":"ENG","IsA":false,"ID":"20396","FN":"Lee"},{"LN":"Fisher","SN":"FISHER","Nat":"ENG","IsA":false,"ID":"27896","FN":"Ross"},{"LN":"McDowell","SN":"MCDOWELL","Nat":"NIR","IsA":false,"ID":"25572","FN":"Graeme"},{"LN":"Willett","SN":"WILLETT","Nat":"ENG","IsA":false,"ID":"32139","FN":"Danny"},{"LN":"Johnson","SN":"JOHNSON Z","Nat":"USA","IsA":false,"ID":"24024","FN":"Zach"},{"LN":"Cabrera","SN":"CABRERA","Nat":"ARG","IsA":false,"ID":"20848","FN":"Angel"},{"LN":"Kuchar","SN":"KUCHAR","Nat":"USA","IsA":false,"ID":"23108","FN":"Matt"},{"LN":"Molinari","SN":"MOLINARI","Nat":"ITA","IsA":false,"ID":"25198","FN":"Francesco"},{"LN":"Reed","SN":"REED","Nat":"USA","IsA":false,"ID":"34360","FN":"Patrick"},{"LN":"Kaymer","SN":"KAYMER","Nat":"GER","IsA":false,"ID":"27408","FN":"Martin"},{"LN":"Spieth","SN":"SPIETH","Nat":"USA","IsA":false,"ID":"34046","FN":"Jordan"},{"LN":"Johnson","SN":"JOHNSON D","Nat":"USA","IsA":false,"ID":"30925","FN":"Dustin"},{"LN":"Niemann","SN":"NIEMANN","Nat":"CHI","IsA":true,"ID":"45486","FN":"Joaquin"},{"LN":"Jaeger","SN":"JAEGER","Nat":"GER","IsA":false,"ID":"36799","FN":"Stephan"},{"LN":"Stalter","SN":"STALTER","Nat":"FRA","IsA":false,"ID":"40104","FN":"Joel"},{"LN":"Miernicki","SN":"MIERNICKI","Nat":"USA","IsA":false,"ID":"34305","FN":"Daniel"},{"LN":"Theegala","SN":"THEEGALA","Nat":"USA","IsA":true,"ID":"51634","FN":"Sahith"},{"LN":"Maguire","SN":"MAGUIRE","Nat":"USA","IsA":false,"ID":"47996","FN":"Jack"},{"LN":"Conners","SN":"CONNERS","Nat":"CAN","IsA":false,"ID":"39997","FN":"Corey"},{"LN":"Kohles","SN":"KOHLES","Nat":"USA","IsA":false,"ID":"36884","FN":"Ben"},{"LN":"Pepperell","SN":"PEPPERELL","Nat":"ENG","IsA":false,"ID":"34709","FN":"Eddie"},{"LN":"Kim","SN":"KIM C","Nat":"USA","IsA":false,"ID":"34587","FN":"Chan"},{"LN":"Vegas","SN":"VEGAS","Nat":"VEN","IsA":false,"ID":"27064","FN":"Jhonattan"},{"LN":"Ikeda","SN":"IKEDA","Nat":"JPN","IsA":false,"ID":"26908","FN":"Yuta"},{"LN":"O'Hair","SN":"O HAIR","Nat":"USA","IsA":false,"ID":"24140","FN":"Sean"},{"LN":"Stuard","SN":"STUARD","Nat":"USA","IsA":false,"ID":"31560","FN":"Brian"},{"LN":"Coetzee","SN":"COETZEE","Nat":"RSA","IsA":false,"ID":"28937","FN":"George"},{"LN":"Leishman","SN":"LEISHMAN","Nat":"AUS","IsA":false,"ID":"26851","FN":"Marc"},{"LN":"Perez","SN":"PEREZ","Nat":"USA","IsA":false,"ID":"24361","FN":"Pat"},{"LN":"Kim","SN":"KIM S W","Nat":"KOR","IsA":false,"ID":"37455","FN":"Si Woo"},{"LN":"Henley","SN":"HENLEY","Nat":"USA","IsA":false,"ID":"34098","FN":"Russell"},{"LN":"English","SN":"ENGLISH","Nat":"USA","IsA":false,"ID":"34099","FN":"Harris"},{"LN":"Watson","SN":"WATSON","Nat":"USA","IsA":false,"ID":"25804","FN":"Bubba"},{"LN":"Scott","SN":"SCOTT","Nat":"AUS","IsA":false,"ID":"24502","FN":"Adam"},{"LN":"Garcia","SN":"GARCIA","Nat":"ESP","IsA":false,"ID":"21209","FN":"Sergio"},{"LN":"Stenson","SN":"STENSON","Nat":"SWE","IsA":false,"ID":"21528","FN":"Henrik"},{"LN":"Schwartzel","SN":"SCHWARTZEL","Nat":"RSA","IsA":false,"ID":"26331","FN":"Charl"},{"LN":"Oosthuizen","SN":"OOSTHUIZEN","Nat":"RSA","IsA":false,"ID":"26329","FN":"Louis"},{"LN":"Fitzpatrick","SN":"FITZPATRICK","Nat":"ENG","IsA":false,"ID":"40098","FN":"Matt"},{"LN":"Uihlein","SN":"UIHLEIN","Nat":"USA","IsA":false,"ID":"29484","FN":"Peter"},{"LN":"Day","SN":"DAY","Nat":"AUS","IsA":false,"ID":"28089","FN":"Jason"},{"LN":"Rose","SN":"ROSE","Nat":"ENG","IsA":false,"ID":"22405","FN":"Justin"},{"LN":"McIlroy","SN":"MCILROY","Nat":"NIR","IsA":false,"ID":"28237","FN":"Rory"},{"LN":"Stricker","SN":"STRICKER","Nat":"USA","IsA":false,"ID":"06527","FN":"Steve"},{"LN":"Cink","SN":"CINK","Nat":"USA","IsA":false,"ID":"20229","FN":"Stewart"},{"LN":"Brehm","SN":"BREHM","Nat":"USA","IsA":false,"ID":"28420","FN":"Ryan"},{"LN":"Oda","SN":"ODA","Nat":"USA","IsA":true,"ID":"35947","FN":"John"},{"LN":"Randolph","SN":"RANDOLPH","Nat":"USA","IsA":false,"ID":"34358","FN":"Jonathan"},{"LN":"Andersen","SN":"ANDERSEN","Nat":"USA","IsA":true,"ID":"52370","FN":"Mason"},{"LN":"Barron","SN":"BARRON","Nat":"USA","IsA":false,"ID":"36963","FN":"Derek"},{"LN":"Robledo","SN":"ROBLEDO","Nat":"USA","IsA":false,"ID":"47622","FN":"Roman"},{"LN":"Ormsby","SN":"ORMSBY","Nat":"AUS","IsA":false,"ID":"26341","FN":"Wade"},{"LN":"Bekker","SN":"BEKKER","Nat":"RSA","IsA":false,"ID":"31678","FN":"Oliver"},{"LN":"Thompson","SN":"THOMPSON","Nat":"USA","IsA":false,"ID":"22582","FN":"Kyle"},{"LN":"Stone","SN":"STONE","Nat":"RSA","IsA":false,"ID":"35225","FN":"Brandon"},{"LN":"Merritt","SN":"MERRITT","Nat":"USA","IsA":false,"ID":"32640","FN":"Troy"},{"LN":"Summerhays","SN":"SUMMERHAYS","Nat":"USA","IsA":false,"ID":"25834","FN":"Daniel"},{"LN":"Levy","SN":"LEVY","Nat":"FRA","IsA":false,"ID":"34579","FN":"Alexander"},{"LN":"McGirt","SN":"MCGIRT","Nat":"USA","IsA":false,"ID":"31202","FN":"William"},{"LN":"Bradley","SN":"BRADLEY","Nat":"USA","IsA":false,"ID":"33141","FN":"Keegan"},{"LN":"Na","SN":"NA","Nat":"USA","IsA":false,"ID":"25396","FN":"Kevin"},{"LN":"Dalke","SN":"DALKE","Nat":"USA","IsA":true,"ID":"49826","FN":"Brad"},{"LN":"Bryan","SN":"BRYAN","Nat":"USA","IsA":false,"ID":"48084","FN":"Wesley"},{"LN":"Flanagan","SN":"FLANAGAN","Nat":"AUS","IsA":false,"ID":"27561","FN":"Nick"},{"LN":"Ramsay","SN":"RAMSAY","Nat":"SCO","IsA":false,"ID":"29531","FN":"Richie"},{"LN":"DeChambeau","SN":"DECHAMBEAU","Nat":"USA","IsA":false,"ID":"47959","FN":"Bryson"},{"LN":"Berger","SN":"BERGER","Nat":"USA","IsA":false,"ID":"40026","FN":"Daniel"},{"LN":"Castro","SN":"CASTRO","Nat":"USA","IsA":false,"ID":"32200","FN":"Roberto"},{"LN":"Haas","SN":"HAAS","Nat":"USA","IsA":false,"ID":"24924","FN":"Bill"},{"LN":"Pan","SN":"PAN","Nat":"TPE","IsA":false,"ID":"29908","FN":"C.T."},{"LN":"Piercy","SN":"PIERCY","Nat":"USA","IsA":false,"ID":"25818","FN":"Scott"},{"LN":"Lowry","SN":"LOWRY","Nat":"IRL","IsA":false,"ID":"33204","FN":"Shane"},{"LN":"Furyk","SN":"FURYK","Nat":"USA","IsA":false,"ID":"10809","FN":"Jim"},{"LN":"Walker","SN":"WALKER","Nat":"USA","IsA":false,"ID":"25632","FN":"Jimmy"},{"LN":"Thomas","SN":"THOMAS","Nat":"USA","IsA":false,"ID":"33448","FN":"Justin"},{"LN":"Casey","SN":"CASEY","Nat":"ENG","IsA":false,"ID":"25364","FN":"Paul"},{"LN":"Chappell","SN":"CHAPPELL","Nat":"USA","IsA":false,"ID":"32366","FN":"Kevin"},{"LN":"McNealy","SN":"MCNEALY","Nat":"USA","IsA":true,"ID":"46442","FN":"Maverick"},{"LN":"Wiesberger","SN":"WIESBERGER","Nat":"AUT","IsA":false,"ID":"29454","FN":"Bernd"},{"LN":"Schauffele","SN":"SCHAUFFELE","Nat":"USA","IsA":false,"ID":"48081","FN":"Xander"},{"LN":"Mullinax","SN":"MULLINAX","Nat":"USA","IsA":false,"ID":"46601","FN":"Trey"},{"LN":"Champ","SN":"CHAMP","Nat":"USA","IsA":true,"ID":"52372","FN":"Cameron"},{"LN":"Ryder","SN":"RYDER","Nat":"USA","IsA":false,"ID":"37275","FN":"Sam"},{"LN":"Smalley","SN":"SMALLEY","Nat":"USA","IsA":true,"ID":"46340","FN":"Alex"},{"LN":"Pope","SN":"POPE","Nat":"USA","IsA":false,"ID":"33592","FN":"Andy"},{"LN":"Miyazato","SN":"MIYAZATO","Nat":"JPN","IsA":false,"ID":"23821","FN":"Yusaku"},{"LN":"Lingmerth","SN":"LINGMERTH","Nat":"SWE","IsA":false,"ID":"34409","FN":"David"},{"LN":"Cabrera Bello","SN":"CABRERA BEL","Nat":"ESP","IsA":false,"ID":"26499","FN":"Rafa"},{"LN":"Kokrak","SN":"KOKRAK","Nat":"USA","IsA":false,"ID":"30944","FN":"Jason"},{"LN":"Knox","SN":"KNOX","Nat":"SCO","IsA":false,"ID":"33122","FN":"Russell"},{"LN":"Crawford","SN":"CRAWFORD","Nat":"USA","IsA":true,"ID":"50488","FN":"Christopher"},{"LN":"Wallace","SN":"WALLACE","Nat":"ENG","IsA":false,"ID":"48887","FN":"Matt"},{"LN":"Rahm","SN":"RAHM","Nat":"ESP","IsA":false,"ID":"46970","FN":"Jon"},{"LN":"Johnston","SN":"JOHNSTON","Nat":"ENG","IsA":false,"ID":"34242","FN":"Andrew"},{"LN":"Scheffler","SN":"SCHEFFLER","Nat":"USA","IsA":true,"ID":"46046","FN":"Scottie"},{"LN":"Putnam","SN":"PUTNAM","Nat":"USA","IsA":false,"ID":"28486","FN":"Michael"},{"LN":"Kodaira","SN":"KODAIRA","Nat":"JPN","IsA":false,"ID":"32816","FN":"Satoshi"},{"LN":"Steele","SN":"STEELE","Nat":"USA","IsA":false,"ID":"29518","FN":"Brendan"},{"LN":"An","SN":"AN","Nat":"KOR","IsA":false,"ID":"33948","FN":"Byeong Hun"},{"LN":"Grillo","SN":"GRILLO","Nat":"ARG","IsA":false,"ID":"31646","FN":"Emiliano"},{"LN":"Love IV","SN":"LOVE IV","Nat":"USA","IsA":false,"ID":"39004","FN":"Davis"},{"LN":"Kim","SN":"KIM W","Nat":"KOR","IsA":false,"ID":"37454","FN":"Whee"},{"LN":"Palmer","SN":"PALMER","Nat":"USA","IsA":false,"ID":"23320","FN":"Ryan"},{"LN":"Light","SN":"LIGHT","Nat":"USA","IsA":false,"ID":"47610","FN":"Tyler"},{"LN":"Bourdy","SN":"BOURDY","Nat":"FRA","IsA":false,"ID":"26525","FN":"Gregory"},{"LN":"Wood","SN":"WOOD","Nat":"ENG","IsA":false,"ID":"22000","FN":"Chris"},{"LN":"Diaz","SN":"DIAZ","Nat":"MEX","IsA":false,"ID":"35376","FN":"Roberto"}],"Fed":"BallPlots","Rs":[{"Hs":[{"Rnk":"4","Par":4,"HY":432,"HPs":[{"HSc":"4","Sks":[{"No":1,"ZID":1,"IsIn":false,"Y":457185.911,"X":2392522.822,"DTP":6133.1,"Dis":9152.3},{"No":2,"ZID":6,"IsIn":false,"Y":457431.87,"X":2392072.731,"DTP":290.2,"Dis":6154.9},{"No":3,"ZID":2,"IsIn":false,"Y":457455.556,"X":2392087.807,"DTP":43.2,"Dis":337.0},{"No":4,"ZID":0,"IsIn":true,"Y":457452.093,"X":2392086.312,"DTP":0,"Dis":43.2}],"HPR":"0","Pos":"T34","TPR":"0","ID":"29221"},{"HSc":"5","Sks":[{"No":1,"ZID":20,"IsIn":false,"Y":457148.219,"X":2392388.408,"DTP":5139.7,"Dis":10269.2},{"No":2,"ZID":18,"IsIn":false,"Y":457401.938,"X":2392068.89,"DTP":635.2,"Dis":4896.0},{"No":3,"ZID":6,"IsIn":false,"Y":457465.863,"X":2392099.2,"DTP":224.4,"Dis":849.0},{"No":4,"ZID":2,"IsIn":false,"Y":457446.321,"X":2392076.946,"DTP":129.9,"Dis":355.6},{"No":5,"ZID":0,"IsIn":true,"Y":457452.093,"X":2392086.312,"DTP":0,"Dis":129.9}],"HPR":"1","Pos":"67","TPR":"15","ID":"47610"},{"HSc":"4","Sks":[{"No":1,"ZID":3,"IsIn":false,"Y":457273.535,"X":2392438.83,"DTP":4740.7,"Dis":10593.1},{"No":2,"ZID":18,"IsIn":false,"Y":457458.175,"X":2392108.91,"DTP":284.2,"Dis":4537.0},{"No":3,"ZID":2,"IsIn":false,"Y":457447.512,"X":2392085.553,"DTP":53.6,"Dis":313.3},{"No":4,"ZID":0,"IsIn":true,"Y":457452.093,"X":2392086.312,"DTP":0,"Dis":53.6}],"HPR":"0","Pos":"T24","TPR":"-3","ID":"23108"},{"HSc":"4","Sks":[{"No":1,"ZID":1,"IsIn":false,"Y":457215.703,"X":2392469.746,"DTP":5403.3,"Dis":9878.1},{"No":2,"ZID":2,"IsIn":false,"Y":457438.284,"X":2392080.109,"DTP":179.6,"Dis":5384.8},{"No":3,"ZID":2,"IsIn":false,"Y":457453.297,"X":2392086.689,"DTP":13.0,"Dis":196.7},{"No":4,"ZID":0,"IsIn":true,"Y":457452.093,"X":2392086.312,"DTP":0,"Dis":13.0}],"HPR":"0","Pos":"T29","TPR":"-1","ID":"24024"},{"HSc":"4","Sks":[{"No":1,"ZID":1,"IsIn":false,"Y":457233.021,"X":2392493.599,"DTP":5547.5,"Dis":9772.7},{"No":2,"ZID":1,"IsIn":false,"Y":457480.304,"X":2392115.824,"DTP":489.6,"Dis":5418.3},{"No":3,"ZID":2,"IsIn":false,"Y":457446.132,"X":2392078.039,"DTP":120.3,"Dis":612.9},{"No":4,"ZID":0,"IsIn":true,"Y":457452.093,"X":2392086.312,"DTP":0,"Dis":120.3}],"HPR":"0","Pos":"T53","TPR":"6","ID":"30944"},{"HSc":"5","Sks":[{"No":1,"ZID":27,"IsIn":false,"Y":457115.05,"X":2392490.58,"DTP":6313.9,"Dis":9007.7},{"No":2,"ZID":2,"IsIn":false,"Y":457517.536,"X":2392059.243,"DTP":847.7,"Dis":7079.5},{"No":3,"ZID":2,"IsIn":false,"Y":457445.539,"X":2392084.244,"DTP":80.4,"Dis":914.6},{"No":4,"ZID":2,"IsIn":false,"Y":457456.448,"X":2392086.906,"DTP":50.7,"Dis":134.8},{"No":5,"ZID":0,"IsIn":true,"Y":457452.093,"X":2392086.312,"DTP":0,"Dis":50.7}],"HPR":"1","Pos":"52","TPR":"4","ID":"31323"},{"HSc":"4","Sks":[{"No":1,"ZID":1,"IsIn":false,"Y":457240.471,"X":2392408.261,"DTP":4621.4,"Dis":10652.8},{"No":2,"ZID":2,"IsIn":false,"Y":457440.816,"X":2392076.873,"DTP":174.4,"Dis":4647.2},{"No":3,"ZID":2,"IsIn":false,"Y":457453.928,"X":2392088.604,"DTP":33.1,"Dis":211.2},{"No":4,"ZID":0,"IsIn":true,"Y":457452.093,"X":2392086.312,"DTP":0,"Dis":33.1}],"HPR":"0","Pos":"T43","TPR":"2","ID":"26499"},{"HSc":"4","Sks":[{"No":1,"ZID":4,"IsIn":false,"Y":457099.168,"X":2392459.746,"DTP":6163.7,"Dis":9236.0},{"No":2,"ZID":18,"IsIn":false,"Y":457468.608,"X":2392107.587,"DTP":326.3,"Dis":6125.2},{"No":3,"ZID":2,"IsIn":false,"Y":457443.134,"X":2392079.053,"DTP":136.3,"Dis":462.9},{"No":4,"ZID":0,"IsIn":true,"Y":457452.093,"X":2392086.312,"DTP":0,"Dis":136.3}],"HPR":"0","Pos":"66","TPR":"13","ID":"46402"},{"HSc":"4","Sks":[{"No":1,"ZID":1,"IsIn":false,"Y":457299.649,"X":2392319.952,"DTP":3347.3,"Dis":11929.6},{"No":2,"ZID":2,"IsIn":false,"Y":457466.488,"X":2392071.695,"DTP":244.1,"Dis":3590.7},{"No":3,"ZID":2,"IsIn":false,"Y":457450.378,"X":2392084.975,"DTP":24.0,"Dis":250.6},{"No":4,"ZID":0,"IsIn":true,"Y":457452.093,"X":2392086.312,"DTP":0,"Dis":24.0}],"HPR":"0","Pos":"T53","TPR":"6","ID":"28420"},{"HSc":"4","Sks":[{"No":1,"ZID":1,"IsIn":false,"Y":457160.764,"X":2392498.468,"DTP":6054.6,"Dis":9218.7},{"No":2,"ZID":2,"IsIn":false,"Y":457477.028,"X":2392050.658,"DTP":520.0,"Dis":6578.8},{"No":3,"ZID":2,"IsIn":false,"Y":457451.103,"X":2392082.077,"DTP":50.1,"Dis":488.8},{"No":4,"ZID":0,"IsIn":true,"Y":457452.093,"X":2392086.312,"DTP":0,"Dis":50.1}],"HPR":"0","Pos":"T38","TPR":"1","ID":"46048"},{"HSc":"4","Sks":[{"No":1,"ZID":1,"IsIn":false,"Y":457171.017,"X":2392433.592,"DTP":5359.2,"Dis":9940.5},{"No":2,"ZID":2,"IsIn":false,"Y":457477.991,"X":2392077.111,"DTP":327.8,"Dis":5645.3},{"No":3,"ZID":2,"IsIn":false,"Y":457449.176,"X":2392083.731,"DTP":44.6,"Dis":354.9},{"No":4,"ZID":0,"IsIn":true,"Y":457452.093,"X":2392086.312,"DTP":0,"Dis":44.6}],"HPR":"0","Pos":"28","TPR":"-2","ID":"06527"},{"HSc":"4","Sks":[{"No":1,"ZID":1,"IsIn":false,"Y":457274.398,"X":2392383.21,"DTP":4150.8,"Dis":11133.9},{"No":2,"ZID":2,"IsIn":false,"Y":457479.934,"X":2392078.649,"DTP":344.5,"Dis":4409.7},{"No":3,"ZID":2,"IsIn":false,"Y":457450.976,"X":2392083.51,"DTP":34.1,"Dis":352.4},{"No":4,"ZID":0,"IsIn":true,"Y":457452.093,"X":2392086.312,"DTP":0,"Dis":34.1}],"HPR":"0","Pos":"T48","TPR":"3","ID":"33204"},{"HSc":"4","Sks":[{"No":1,"ZID":1,"IsIn":false,"Y":457217.64,"X":2392377.777,"DTP":4487.0,"Dis":10806.3},{"No":2,"ZID":2,"IsIn":false,"Y":457468.8,"X":2392065.956,"DTP":314.0,"Dis":4805.0},{"No":3,"ZID":2,"IsIn":false,"Y":457449.134,"X":2392086.307,"DTP":33.4,"Dis":339.7},{"No":4,"ZID":0,"IsIn":true,"Y":457452.093,"X":2392086.312,"DTP":0,"Dis":33.4}],"HPR":"0","Pos":"65","TPR":"12","ID":"25834"},{"HSc":"4","Sks":[{"No":1,"ZID":1,"IsIn":false,"Y":457266.414,"X":2392334.075,"DTP":3714.7,"Dis":11565.8},{"No":2,"ZID":2,"IsIn":false,"Y":457468.585,"X":2392063.582,"DTP":334.9,"Dis":4053.5},{"No":3,"ZID":2,"IsIn":false,"Y":457452.984,"X":2392086.504,"DTP":8.8,"Dis":332.8},{"No":4,"ZID":0,"IsIn":true,"Y":457452.093,"X":2392086.312,"DTP":0,"Dis":8.8}],"HPR":"0","Pos":"T60","TPR":"9","ID":"33141"},{"HSc":"4","Sks":[{"No":1,"ZID":1,"IsIn":false,"Y":457282.411,"X":2392394.279,"DTP":4217.8,"Dis":11082.2},{"No":2,"ZID":2,"IsIn":false,"Y":457463.051,"X":2392066.676,"DTP":267.8,"Dis":4489.6},{"No":3,"ZID":2,"IsIn":false,"Y":457447.257,"X":2392086.927,"DTP":56.4,"Dis":308.2},{"No":4,"ZID":0,"IsIn":true,"Y":457452.093,"X":2392086.312,"DTP":0,"Dis":56.4}],"HPR":"0","Pos":"T38","TPR":"1","ID":"34046"},{"HSc":"4","Sks":[{"No":1,"ZID":1,"IsIn":false,"Y":457277.206,"X":2392376.777,"DTP":4067.3,"Dis":11216.4},{"No":2,"ZID":2,"IsIn":false,"Y":457467.635,"X":2392087.273,"DTP":184.8,"Dis":4158.9},{"No":3,"ZID":2,"IsIn":false,"Y":457452.378,"X":2392085.808,"DTP":4.8,"Dis":184.0},{"No":4,"ZID":0,"IsIn":true,"Y":457452.093,"X":2392086.312,"DTP":0,"Dis":4.8}],"HPR":"0","Pos":"T60","TPR":"9","ID":"36799"},{"HSc":"3","Sks":[{"No":1,"ZID":1,"IsIn":false,"Y":457246.731,"X":2392358.178,"DTP":4087.4,"Dis":11194.0},{"No":2,"ZID":2,"IsIn":false,"Y":457457.146,"X":2392093.412,"DTP":102.5,"Dis":4059.2},{"No":3,"ZID":0,"IsIn":true,"Y":457452.093,"X":2392086.312,"DTP":0,"Dis":102.5}],"HPR":"-1","Pos":"T58","TPR":"8","ID":"29478"},{"HSc":"4","Sks":[{"No":1,"ZID":3,"IsIn":false,"Y":457294.765,"X":2392402.323,"DTP":4234.3,"Dis":11093.5},{"No":2,"ZID":18,"IsIn":false,"Y":457469.061,"X":2392110.553,"DTP":358.6,"Dis":4078.4},{"No":3,"ZID":2,"IsIn":false,"Y":457448.992,"X":2392085.0,"DTP":38.3,"Dis":395.2},{"No":4,"ZID":0,"IsIn":true,"Y":457452.093,"X":2392086.312,"DTP":0,"Dis":38.3}],"HPR":"0","Pos":"T43","TPR":"2","ID":"29974"},{"HSc":"4","Sks":[{"No":1,"ZID":27,"IsIn":false,"Y":457192.703,"X":2392349.645,"DTP":4433.6,"Dis":10938.1},{"No":2,"ZID":2,"IsIn":false,"Y":457457.348,"X":2392098.857,"DTP":161.2,"Dis":4375.3},{"No":3,"ZID":2,"IsIn":false,"Y":457454.12,"X":2392084.38,"DTP":31.5,"Dis":178.0},{"No":4,"ZID":0,"IsIn":true,"Y":457452.093,"X":2392086.312,"DTP":0,"Dis":31.5}],"HPR":"0","Pos":"T55","TPR":"7","ID":"20396"},{"HSc":"4","Sks":[{"No":1,"ZID":4,"IsIn":false,"Y":457357.574,"X":2392437.099,"DTP":4357.6,"Dis":11249.9},{"No":2,"ZID":18,"IsIn":false,"Y":457462.459,"X":2392104.297,"DTP":250.7,"Dis":4187.3},{"No":3,"ZID":2,"IsIn":false,"Y":457464.073,"X":2392096.549,"DTP":187.0,"Dis":102.9},{"No":4,"ZID":0,"IsIn":true,"Y":457452.093,"X":2392086.312,"DTP":0,"Dis":187.0}],"HPR":"0","Pos":"68","TPR":"22","ID":"35296"},{"HSc":"5","Sks":[{"No":1,"ZID":1,"IsIn":false,"Y":457250.903,"X":2392316.753,"DTP":3670.3,"Dis":11639.7},{"No":2,"ZID":18,"IsIn":false,"Y":457459.444,"X":2392108.217,"DTP":280.9,"Dis":3539.4},{"No":3,"ZID":2,"IsIn":false,"Y":457451.567,"X":2392070.769,"DTP":184.5,"Dis":463.0},{"No":4,"ZID":2,"IsIn":false,"Y":457451.49,"X":2392085.582,"DTP":9.3,"Dis":177.8},{"No":5,"ZID":0,"IsIn":true,"Y":457452.093,"X":2392086.312,"DTP":0,"Dis":9.3}],"HPR":"1","Pos":"T48","TPR":"3","ID":"20229"},{"HSc":"3","Sks":[{"No":1,"ZID":1,"IsIn":false,"Y":457202.612,"X":2392513.442,"DTP":5933.7,"Dis":9362.1},{"No":2,"ZID":2,"IsIn":false,"Y":457471.641,"X":2392043.645,"DTP":561.1,"Dis":6496.5},{"No":3,"ZID":0,"IsIn":true,"Y":457452.093,"X":2392086.312,"DTP":0,"Dis":561.1}],"HPR":"-1","Pos":"T24","TPR":"-3","ID":"32366"},{"HSc":"4","Sks":[{"No":1,"ZID":1,"IsIn":false,"Y":457124.525,"X":2392543.856,"DTP":6750.5,"Dis":8524.6},{"No":2,"ZID":2,"IsIn":false,"Y":457483.831,"X":2392041.233,"DTP":659.5,"Dis":7414.2},{"No":3,"ZID":2,"IsIn":false,"Y":457451.13,"X":2392084.963,"DTP":17.8,"Dis":655.3},{"No":4,"ZID":0,"IsIn":true,"Y":457452.093,"X":2392086.312,"DTP":0,"Dis":17.8}],"HPR":"0","Pos":"T29","TPR":"-1","ID":"10809"},{"HSc":"3","Sks":[{"No":1,"ZID":1,"IsIn":false,"Y":457204.227,"X":2392516.298,"DTP":5953.6,"Dis":9346.3},{"No":2,"ZID":2,"IsIn":false,"Y":457457.377,"X":2392078.194,"DTP":114.1,"Dis":6071.8},{"No":3,"ZID":0,"IsIn":true,"Y":457452.093,"X":2392086.312,"DTP":0,"Dis":114.1}],"HPR":"-1","Pos":"T20","TPR":"-4","ID":"26329"},{"HSc":"4","Sks":[{"No":1,"ZID":1,"IsIn":false,"Y":457200.601,"X":2392492.091,"DTP":5726.6,"Dis":9554.1},{"No":2,"ZID":2,"IsIn":false,"Y":457469.623,"X":2392066.636,"DTP":314.2,"Dis":6040.5},{"No":3,"ZID":2,"IsIn":false,"Y":457447.375,"X":2392086.704,"DTP":54.7,"Dis":359.6},{"No":4,"ZID":0,"IsIn":true,"Y":457452.093,"X":2392086.312,"DTP":0,"Dis":54.7}],"HPR":"0","Pos":"T38","TPR":"1","ID":"25396"},{"HSc":"4","Sks":[{"No":1,"ZID":1,"IsIn":false,"Y":457229.315,"X":2392298.648,"DTP":3693.0,"Dis":11691.0},{"No":2,"ZID":2,"IsIn":false,"Y":457456.044,"X":2392093.093,"DTP":92.1,"Dis":3674.3},{"No":3,"ZID":2,"IsIn":false,"Y":457456.334,"X":2392086.457,"DTP":48.8,"Dis":79.7},{"No":4,"ZID":0,"IsIn":true,"Y":457452.093,"X":2392086.312,"DTP":0,"Dis":48.8}],"HPR":"0","Pos":"T43","TPR":"2","ID":"35225"},{"HSc":"4","Sks":[{"No":1,"ZID":1,"IsIn":false,"Y":457242.24,"X":2392466.383,"DTP":5207.8,"Dis":10099.8},{"No":2,"ZID":2,"IsIn":false,"Y":457466.877,"X":2392070.609,"DTP":256.8,"Dis":5461.0},{"No":3,"ZID":2,"IsIn":false,"Y":457450.799,"X":2392085.76,"DTP":14.8,"Dis":265.2},{"No":4,"ZID":0,"IsIn":true,"Y":457452.093,"X":2392086.312,"DTP":0,"Dis":14.8}],"HPR":"0","Pos":"T29","TPR":"-1","ID":"27936"},{"HSc":"4","Sks":[{"No":1,"ZID":4,"IsIn":false,"Y":457314.942,"X":2392496.584,"DTP":5189.0,"Dis":10375.6},{"No":2,"ZID":18,"IsIn":false,"Y":457418.222,"X":2392144.359,"DTP":806.6,"Dis":4405.5},{"No":3,"ZID":2,"IsIn":false,"Y":457446.601,"X":2392075.442,"DTP":144.1,"Dis":896.6},{"No":4,"ZID":0,"IsIn":true,"Y":457452.093,"X":2392086.312,"DTP":0,"Dis":144.1}],"HPR":"0","Pos":"T9","TPR":"-8","ID":"34360"},{"HSc":"4","Sks":[{"No":1,"ZID":1,"IsIn":false,"Y":457220.327,"X":2392525.479,"DTP":5956.8,"Dis":9377.5},{"No":2,"ZID":18,"IsIn":false,"Y":457445.383,"X":2392113.23,"DTP":332.4,"Dis":5636.3},{"No":3,"ZID":2,"IsIn":false,"Y":457454.384,"X":2392078.942,"DTP":90.5,"Dis":426.5},{"No":4,"ZID":0,"IsIn":true,"Y":457452.093,"X":2392086.312,"DTP":0,"Dis":90.5}],"HPR":"0","Pos":"T38","TPR":"1","ID":"28486"},{"HSc":"4","Sks":[{"No":1,"ZID":1,"IsIn":false,"Y":457171.44,"X":2392491.541,"DTP":5913.0,"Dis":9359.1},{"No":2,"ZID":2,"IsIn":false,"Y":457502.594,"X":2392065.256,"DTP":654.5,"Dis":6477.6},{"No":3,"ZID":2,"IsIn":false,"Y":457451.631,"X":2392079.532,"DTP":79.4,"Dis":635.1},{"No":4,"ZID":0,"IsIn":true,"Y":457452.093,"X":2392086.312,"DTP":0,"Dis":79.4}],"HPR":"0","Pos":"64","TPR":"10","ID":"47663"},{"HSc":"4","Sks":[{"No":1,"ZID":1,"IsIn":false,"Y":457187.373,"X":2392491.953,"DTP":5810.4,"Dis":9463.4},{"No":2,"ZID":2,"IsIn":false,"Y":457487.099,"X":2392057.715,"DTP":540.3,"Dis":6331.6},{"No":3,"ZID":2,"IsIn":false,"Y":457449.528,"X":2392086.73,"DTP":29.1,"Dis":569.7},{"No":4,"ZID":0,"IsIn":true,"Y":457452.093,"X":2392086.312,"DTP":0,"Dis":29.1}],"HPR":"0","Pos":"T48","TPR":"3","ID":"37454"},{"HSc":"5","Sks":[{"No":1,"ZID":1,"IsIn":false,"Y":457269.038,"X":2392344.563,"DTP":3797.7,"Dis":11478.6},{"No":2,"ZID":2,"IsIn":false,"Y":457470.262,"X":2392059.556,"DTP":386.0,"Dis":4187.6},{"No":3,"ZID":2,"IsIn":false,"Y":457453.254,"X":2392089.696,"DTP":40.8,"Dis":415.3},{"No":4,"ZID":2,"IsIn":false,"Y":457451.514,"X":2392082.779,"DTP":40.9,"Dis":85.6},{"No":5,"ZID":0,"IsIn":true,"Y":457452.093,"X":2392086.312,"DTP":0,"Dis":40.9}],"HPR":"1","Pos":"T20","TPR":"-4","ID":"46601"},{"HSc":"5","Sks":[{"No":1,"ZID":1,"IsIn":false,"Y":457173.392,"X":2392548.921,"DTP":6478.8,"Dis":8811.2},{"No":2,"ZID":27,"IsIn":false,"Y":457436.166,"X":2392037.078,"DTP":624.0,"Dis":6904.6},{"No":3,"ZID":2,"IsIn":false,"Y":457457.632,"X":2392089.092,"DTP":72.3,"Dis":680.2},{"No":4,"ZID":2,"IsIn":false,"Y":457448.177,"X":2392084.015,"DTP":52.4,"Dis":128.8},{"No":5,"ZID":0,"IsIn":true,"Y":457452.093,"X":2392086.312,"DTP":0,"Dis":52.4}],"HPR":"1","Pos":"T34","TPR":"0","ID":"40098"},{"HSc":"3","Sks":[{"No":1,"ZID":1,"IsIn":false,"Y":457228.18,"X":2392507.996,"DTP":5727.3,"Dis":9600.6},{"No":2,"ZID":2,"IsIn":false,"Y":457446.837,"X":2392091.9,"DTP":90.0,"Dis":5640.6},{"No":3,"ZID":0,"IsIn":true,"Y":457452.093,"X":2392086.312,"DTP":0,"Dis":90.0}],"HPR":"-1","Pos":"T29","TPR":"-1","ID":"46046"},{"HSc":"4","Sks":[{"No":1,"ZID":1,"IsIn":false,"Y":457185.718,"X":2392401.64,"DTP":4951.4,"Dis":10359.6},{"No":2,"ZID":2,"IsIn":false,"Y":457491.965,"X":2392065.741,"DTP":536.3,"Dis":5454.7},{"No":3,"ZID":2,"IsIn":false,"Y":457446.884,"X":2392084.206,"DTP":65.3,"Dis":584.6},{"No":4,"ZID":0,"IsIn":true,"Y":457452.093,"X":2392086.312,"DTP":0,"Dis":65.3}],"HPR":"0","Pos":"T16","TPR":"-6","ID":"34709"},{"HSc":"4","Sks":[{"No":1,"ZID":1,"IsIn":false,"Y":457239.994,"X":2392380.598,"DTP":4351.5,"Dis":10924.6},{"No":2,"ZID":2,"IsIn":false,"Y":457455.142,"X":2392059.948,"DTP":316.4,"Dis":4634.2},{"No":3,"ZID":2,"IsIn":false,"Y":457454.955,"X":2392085.204,"DTP":34.7,"Dis":303.1},{"No":4,"ZID":0,"IsIn":true,"Y":457452.093,"X":2392086.312,"DTP":0,"Dis":34.7}],"HPR":"0","Pos":"T24","TPR":"-3","ID":"47996"},{"HSc":"6","Sks":[{"No":1,"ZID":3,"IsIn":false,"Y":457276.185,"X":2392470.839,"DTP":5072.6,"Dis":10310.8},{"No":2,"ZID":3,"IsIn":false,"Y":457281.922,"X":2392484.762,"DTP":5197.4,"Dis":181.2},{"No":3,"ZID":18,"IsIn":false,"Y":457422.527,"X":2392142.034,"DTP":756.4,"Dis":4445.4},{"No":4,"ZID":2,"IsIn":false,"Y":457479.684,"X":2392042.068,"DTP":623.6,"Dis":1382.6},{"No":5,"ZID":2,"IsIn":false,"Y":457459.788,"X":2392078.805,"DTP":126.9,"Dis":501.3},{"No":6,"ZID":0,"IsIn":true,"Y":457452.093,"X":2392086.312,"DTP":0,"Dis":126.9}],"HPR":"2","Pos":"T55","TPR":"7","ID":"06522"},{"HSc":"5","Sks":[{"No":1,"ZID":1,"IsIn":false,"Y":457232.495,"X":2392429.936,"DTP":4891.6,"Dis":10384.5},{"No":2,"ZID":1,"IsIn":false,"Y":457502.63,"X":2392040.828,"DTP":813.8,"Dis":5684.3},{"No":3,"ZID":2,"IsIn":false,"Y":457454.949,"X":2392081.027,"DTP":70.0,"Dis":748.4},{"No":4,"ZID":2,"IsIn":false,"Y":457452.885,"X":2392090.279,"DTP":46.5,"Dis":113.8},{"No":5,"ZID":0,"IsIn":true,"Y":457452.093,"X":2392086.312,"DTP":0,"Dis":46.5}],"HPR":"1","Pos":"T16","TPR":"-6","ID":"34409"},{"HSc":"5","Sks":[{"No":1,"ZID":1,"IsIn":false,"Y":457199.469,"X":2392428.133,"DTP":5098.5,"Dis":10179.6},{"No":2,"ZID":18,"IsIn":false,"Y":457418.509,"X":2392144.209,"DTP":803.3,"Dis":4303.3},{"No":3,"ZID":2,"IsIn":false,"Y":457471.637,"X":2392072.268,"DTP":286.8,"Dis":1074.5},{"No":4,"ZID":2,"IsIn":false,"Y":457451.252,"X":2392091.295,"DTP":58.5,"Dis":334.7},{"No":5,"ZID":0,"IsIn":true,"Y":457452.093,"X":2392086.312,"DTP":0,"Dis":58.5}],"HPR":"1","Pos":"T60","TPR":"9","ID":"23821"},{"HSc":"4","Sks":[{"No":1,"ZID":1,"IsIn":false,"Y":457250.422,"X":2392317.281,"DTP":3678.9,"Dis":11631.2},{"No":2,"ZID":2,"IsIn":false,"Y":457468.411,"X":2392081.461,"DTP":202.3,"Dis":3855.0},{"No":3,"ZID":2,"IsIn":false,"Y":457452.228,"X":2392086.107,"DTP":1.0,"Dis":202.1},{"No":4,"ZID":0,"IsIn":true,"Y":457452.093,"X":2392086.312,"DTP":0,"Dis":1.0}],"HPR":"0","Pos":"T58","TPR":"8","ID":"24461"},{"HSc":"5","Sks":[{"No":1,"ZID":4,"IsIn":false,"Y":457357.897,"X":2392413.391,"DTP":4082.6,"Dis":11466.8},{"No":2,"ZID":4,"IsIn":false,"Y":457440.555,"X":2392011.497,"DTP":914.1,"Dis":4926.2},{"No":3,"ZID":2,"IsIn":false,"Y":457483.803,"X":2392067.684,"DTP":439.3,"Dis":860.0},{"No":4,"ZID":2,"IsIn":false,"Y":457449.094,"X":2392089.673,"DTP":52.0,"Dis":493.1},{"No":5,"ZID":0,"IsIn":true,"Y":457452.093,"X":2392086.312,"DTP":0,"Dis":52.0}],"HPR":"1","Pos":"T2","TPR":"-11","ID":"33448"},{"HSc":"4","Sks":[{"No":1,"ZID":1,"IsIn":false,"Y":457179.262,"X":2392432.049,"DTP":5283.0,"Dis":10008.7},{"No":2,"ZID":2,"IsIn":false,"Y":457461.66,"X":2392075.442,"DTP":171.7,"Dis":5458.6},{"No":3,"ZID":2,"IsIn":false,"Y":457449.194,"X":2392088.363,"DTP":40.5,"Dis":215.5},{"No":4,"ZID":0,"IsIn":true,"Y":457452.093,"X":2392086.312,"DTP":0,"Dis":40.5}],"HPR":"0","Pos":"T48","TPR":"3","ID":"34358"},{"HSc":"4","Sks":[{"No":1,"ZID":1,"IsIn":false,"Y":457226.489,"X":2392451.413,"DTP":5148.1,"Dis":10132.6},{"No":2,"ZID":2,"IsIn":false,"Y":457440.024,"X":2392088.462,"DTP":145.0,"Dis":5053.4},{"No":3,"ZID":2,"IsIn":false,"Y":457458.825,"X":2392085.64,"DTP":79.1,"Dis":228.1},{"No":4,"ZID":0,"IsIn":true,"Y":457452.093,"X":2392086.312,"DTP":0,"Dis":79.1}],"HPR":"0","Pos":"T60","TPR":"9","ID":"33399"},{"HSc":"4","Sks":[{"No":1,"ZID":3,"IsIn":false,"Y":457290.004,"X":2392428.059,"DTP":4537.7,"Dis":10816.1},{"No":2,"ZID":18,"IsIn":false,"Y":457365.113,"X":2392097.846,"DTP":1051.6,"Dis":4064.1},{"No":3,"ZID":2,"IsIn":false,"Y":457448.577,"X":2392085.096,"DTP":42.5,"Dis":1014.0},{"No":4,"ZID":0,"IsIn":true,"Y":457452.093,"X":2392086.312,"DTP":0,"Dis":42.5}],"HPR":"0","Pos":"T38","TPR":"1","ID":"34242"},{"HSc":"4","Sks":[{"No":1,"ZID":4,"IsIn":false,"Y":457174.998,"X":2392363.682,"DTP":4702.8,"Dis":10685.9},{"No":2,"ZID":4,"IsIn":false,"Y":457429.152,"X":2392120.598,"DTP":493.0,"Dis":4220.3},{"No":3,"ZID":2,"IsIn":false,"Y":457463.017,"X":2392076.246,"DTP":176.2,"Dis":669.7},{"No":4,"ZID":0,"IsIn":true,"Y":457452.093,"X":2392086.312,"DTP":0,"Dis":176.2}],"HPR":"0","Pos":"T43","TPR":"2","ID":"27408"},{"HSc":"5","Sks":[{"No":1,"ZID":4,"IsIn":false,"Y":457267.75,"X":2392490.882,"DTP":5333.0,"Dis":10058.3},{"No":2,"ZID":18,"IsIn":false,"Y":457420.007,"X":2392062.878,"DTP":475.4,"Dis":5451.4},{"No":3,"ZID":2,"IsIn":false,"Y":457440.586,"X":2392090.625,"DTP":145.4,"Dis":415.4},{"No":4,"ZID":2,"IsIn":false,"Y":457453.806,"X":2392087.098,"DTP":20.5,"Dis":164.2},{"No":5,"ZID":0,"IsIn":true,"Y":457452.093,"X":2392086.312,"DTP":0,"Dis":20.5}],"HPR":"1","Pos":"T34","TPR":"0","ID":"32816"},{"HSc":"4","Sks":[{"No":1,"ZID":3,"IsIn":false,"Y":457297.16,"X":2392426.535,"DTP":4484.7,"Dis":10883.2},{"No":2,"ZID":2,"IsIn":false,"Y":457476.08,"X":2392058.264,"DTP":440.8,"Dis":4913.8},{"No":3,"ZID":2,"IsIn":false,"Y":457452.504,"X":2392084.122,"DTP":24.6,"Dis":419.9},{"No":4,"ZID":0,"IsIn":true,"Y":457452.093,"X":2392086.312,"DTP":0,"Dis":24.6}],"HPR":"0","Pos":"T16","TPR":"-6","ID":"21209"},{"HSc":"4","Sks":[{"No":1,"ZID":1,"IsIn":false,"Y":457193.076,"X":2392549.918,"DTP":6370.6,"Dis":8944.8},{"No":2,"ZID":2,"IsIn":false,"Y":457476.868,"X":2392072.459,"DTP":338.6,"Dis":6665.2},{"No":3,"ZID":2,"IsIn":false,"Y":457453.464,"X":2392085.465,"DTP":17.2,"Dis":321.4},{"No":4,"ZID":0,"IsIn":true,"Y":457452.093,"X":2392086.312,"DTP":0,"Dis":17.2}],"HPR":"0","Pos":"T20","TPR":"-4","ID":"29454"},{"HSc":"5","Sks":[{"No":1,"ZID":4,"IsIn":false,"Y":457305.825,"X":2392452.417,"DTP":4728.8,"Dis":10705.3},{"No":2,"ZID":3,"IsIn":false,"Y":457281.21,"X":2392409.836,"DTP":4389.5,"Dis":595.3},{"No":3,"ZID":6,"IsIn":false,"Y":457535.84,"X":2392077.269,"DTP":1008.8,"Dis":5027.0},{"No":4,"ZID":2,"IsIn":false,"Y":457450.541,"X":2392093.494,"DTP":86.1,"Dis":1042.0},{"No":5,"ZID":0,"IsIn":true,"Y":457452.093,"X":2392086.312,"DTP":0,"Dis":86.1}],"HPR":"1","Pos":"T55","TPR":"7","ID":"31202"},{"HSc":"4","Sks":[{"No":1,"ZID":1,"IsIn":false,"Y":457196.54,"X":2392385.756,"DTP":4722.1,"Dis":10590.4},{"No":2,"ZID":2,"IsIn":false,"Y":457473.594,"X":2392056.475,"DTP":439.3,"Dis":5164.1},{"No":3,"ZID":2,"IsIn":false,"Y":457454.501,"X":2392085.277,"DTP":29.4,"Dis":414.7},{"No":4,"ZID":0,"IsIn":true,"Y":457452.093,"X":2392086.312,"DTP":0,"Dis":29.4}],"HPR":"0","Pos":"T6","TPR":"-9","ID":"34098"},{"HSc":"4","Sks":[{"No":1,"ZID":1,"IsIn":false,"Y":457277.406,"X":2392341.79,"DTP":3713.1,"Dis":11562.4},{"No":2,"ZID":2,"IsIn":false,"Y":457477.457,"X":2392068.821,"DTP":367.7,"Dis":4062.1},{"No":3,"ZID":2,"IsIn":false,"Y":457459.576,"X":2392086.695,"DTP":87.8,"Dis":303.4},{"No":4,"ZID":0,"IsIn":true,"Y":457452.093,"X":2392086.312,"DTP":0,"Dis":87.8}],"HPR":"0","Pos":"T9","TPR":"-8","ID":"12716"},{"HSc":"4","Sks":[{"No":1,"ZID":1,"IsIn":false,"Y":457214.415,"X":2392385.003,"DTP":4578.8,"Dis":10712.2},{"No":2,"ZID":2,"IsIn":false,"Y":457465.558,"X":2392073.307,"DTP":222.6,"Dis":4803.7},{"No":3,"ZID":2,"IsIn":false,"Y":457449.258,"X":2392090.789,"DTP":61.5,"Dis":286.9},{"No":4,"ZID":0,"IsIn":true,"Y":457452.093,"X":2392086.312,"DTP":0,"Dis":61.5}],"HPR":"0","Pos":"19","TPR":"-5","ID":"26476"},{"HSc":"5","Sks":[{"No":1,"ZID":3,"IsIn":false,"Y":457272.072,"X":2392447.531,"DTP":4841.8,"Dis":10499.8},{"No":2,"ZID":18,"IsIn":false,"Y":457467.067,"X":2392112.267,"DTP":363.2,"Dis":4654.2},{"No":3,"ZID":2,"IsIn":false,"Y":457483.68,"X":2392097.674,"DTP":400.9,"Dis":270.6},{"No":4,"ZID":2,"IsIn":false,"Y":457453.861,"X":2392088.031,"DTP":27.5,"Dis":376.2},{"No":5,"ZID":0,"IsIn":true,"Y":457452.093,"X":2392086.312,"DTP":0,"Dis":27.5}],"HPR":"1","Pos":"T12","TPR":"-7","ID":"24924"},{"HSc":"4","Sks":[{"No":1,"ZID":1,"IsIn":false,"Y":457174.216,"X":2392422.153,"DTP":5228.7,"Dis":10077.5},{"No":2,"ZID":2,"IsIn":false,"Y":457472.201,"X":2392090.169,"DTP":243.7,"Dis":5353.3},{"No":3,"ZID":2,"IsIn":false,"Y":457450.757,"X":2392086.759,"DTP":14.8,"Dis":260.7},{"No":4,"ZID":0,"IsIn":true,"Y":457452.093,"X":2392086.312,"DTP":0,"Dis":14.8}],"HPR":"0","Pos":"T43","TPR":"2","ID":"34099"},{"HSc":"4","Sks":[{"No":1,"ZID":1,"IsIn":false,"Y":457284.522,"X":2392353.58,"DTP":3784.5,"Dis":11494.5},{"No":2,"ZID":2,"IsIn":false,"Y":457471.887,"X":2392049.877,"DTP":495.5,"Dis":4283.1},{"No":3,"ZID":2,"IsIn":false,"Y":457454.282,"X":2392085.601,"DTP":25.5,"Dis":477.9},{"No":4,"ZID":0,"IsIn":true,"Y":457452.093,"X":2392086.312,"DTP":0,"Dis":25.5}],"HPR":"0","Pos":"T34","TPR":"0","ID":"26851"},{"HSc":"5","Sks":[{"No":1,"ZID":1,"IsIn":false,"Y":457181.687,"X":2392439.656,"DTP":5337.2,"Dis":9947.3},{"No":2,"ZID":2,"IsIn":false,"Y":457439.29,"X":2392075.576,"DTP":198.4,"Dis":5352.0},{"No":3,"ZID":2,"IsIn":false,"Y":457456.565,"X":2392087.224,"DTP":52.7,"Dis":250.1},{"No":4,"ZID":2,"IsIn":false,"Y":457449.428,"X":2392086.307,"DTP":29.9,"Dis":86.4},{"No":5,"ZID":0,"IsIn":true,"Y":457452.093,"X":2392086.312,"DTP":0,"Dis":29.9}],"HPR":"1","Pos":"T9","TPR":"-8","ID":"29518"},{"HSc":"4","Sks":[{"No":1,"ZID":3,"IsIn":false,"Y":457266.724,"X":2392451.472,"DTP":4912.9,"Dis":10423.1},{"No":2,"ZID":2,"IsIn":false,"Y":457471.009,"X":2392058.014,"DTP":406.4,"Dis":5320.6},{"No":3,"ZID":2,"IsIn":false,"Y":457450.755,"X":2392087.028,"DTP":16.1,"Dis":424.6},{"No":4,"ZID":0,"IsIn":true,"Y":457452.093,"X":2392086.312,"DTP":0,"Dis":16.1}],"HPR":"0","Pos":"T12","TPR":"-7","ID":"27649"},{"HSc":"4","Sks":[{"No":1,"ZID":1,"IsIn":false,"Y":457200.991,"X":2392494.663,"DTP":5750.4,"Dis":9531.9},{"No":2,"ZID":18,"IsIn":false,"Y":457463.875,"X":2392107.266,"DTP":291.7,"Dis":5618.4},{"No":3,"ZID":2,"IsIn":false,"Y":457448.063,"X":2392085.982,"DTP":46.4,"Dis":323.2},{"No":4,"ZID":0,"IsIn":true,"Y":457452.093,"X":2392086.312,"DTP":0,"Dis":46.4}],"HPR":"0","Pos":"T6","TPR":"-9","ID":"32839"},{"HSc":"4","Sks":[{"No":1,"ZID":1,"IsIn":false,"Y":457136.278,"X":2392497.412,"DTP":6218.7,"Dis":9069.8},{"No":2,"ZID":1,"IsIn":false,"Y":457495.695,"X":2392137.224,"DTP":804.6,"Dis":6106.4},{"No":3,"ZID":2,"IsIn":false,"Y":457445.126,"X":2392076.849,"DTP":138.9,"Dis":947.2},{"No":4,"ZID":0,"IsIn":true,"Y":457452.093,"X":2392086.312,"DTP":0,"Dis":138.9}],"HPR":"0","Pos":"T12","TPR":"-7","ID":"48081"},{"HSc":"4","Sks":[{"No":1,"ZID":1,"IsIn":false,"Y":457270.922,"X":2392335.242,"DTP":3693.8,"Dis":11584.0},{"No":2,"ZID":2,"IsIn":false,"Y":457469.404,"X":2392073.022,"DTP":259.9,"Dis":3947.5},{"No":3,"ZID":2,"IsIn":false,"Y":457452.363,"X":2392086.927,"DTP":6.0,"Dis":264.0},{"No":4,"ZID":0,"IsIn":true,"Y":457452.093,"X":2392086.312,"DTP":0,"Dis":6.0}],"HPR":"0","Pos":"T29","TPR":"-1","ID":"52372"},{"HSc":"4","Sks":[{"No":1,"ZID":1,"IsIn":false,"Y":457247.985,"X":2392321.398,"DTP":3735.3,"Dis":11573.8},{"No":2,"ZID":2,"IsIn":false,"Y":457441.398,"X":2392098.122,"DTP":189.1,"Dis":3546.2},{"No":3,"ZID":2,"IsIn":false,"Y":457454.525,"X":2392086.701,"DTP":27.5,"Dis":208.8},{"No":4,"ZID":0,"IsIn":true,"Y":457452.093,"X":2392086.312,"DTP":0,"Dis":27.5}],"HPR":"0","Pos":"T12","TPR":"-7","ID":"27141"},{"HSc":"5","Sks":[{"No":1,"ZID":27,"IsIn":false,"Y":457262.876,"X":2392425.476,"DTP":4658.6,"Dis":10641.7},{"No":2,"ZID":1,"IsIn":false,"Y":457485.902,"X":2392037.645,"DTP":709.0,"Dis":5368.8},{"No":3,"ZID":2,"IsIn":false,"Y":457449.407,"X":2392092.352,"DTP":77.2,"Dis":789.2},{"No":4,"ZID":2,"IsIn":false,"Y":457452.915,"X":2392084.396,"DTP":22.9,"Dis":104.3},{"No":5,"ZID":0,"IsIn":true,"Y":457452.093,"X":2392086.312,"DTP":0,"Dis":22.9}],"HPR":"1","Pos":"T6","TPR":"-9","ID":"37455"},{"HSc":"4","Sks":[{"No":1,"ZID":1,"IsIn":false,"Y":457203.34,"X":2392477.261,"DTP":5558.4,"Dis":9718.0},{"No":2,"ZID":1,"IsIn":false,"Y":457195.765,"X":2392486.027,"DTP":5696.0,"Dis":139.1},{"No":3,"ZID":2,"IsIn":false,"Y":457459.942,"X":2392092.458,"DTP":117.6,"Dis":5688.1},{"No":4,"ZID":2,"IsIn":false,"Y":457451.451,"X":2392086.444,"DTP":5.8,"Dis":124.9},{"No":5,"ZID":0,"IsIn":true,"Y":457452.093,"X":2392086.312,"DTP":0,"Dis":5.8}],"HPR":"0","Pos":"T20","TPR":"-4","ID":"29461"},{"HSc":"4","Sks":[{"No":1,"ZID":1,"IsIn":false,"Y":457223.187,"X":2392507.298,"DTP":5748.2,"Dis":9570.4},{"No":2,"ZID":18,"IsIn":false,"Y":457455.271,"X":2392111.944,"DTP":312.8,"Dis":5501.6},{"No":3,"ZID":2,"IsIn":false,"Y":457448.837,"X":2392079.793,"DTP":85.3,"Dis":397.5},{"No":4,"ZID":0,"IsIn":true,"Y":457452.093,"X":2392086.312,"DTP":0,"Dis":85.3}],"HPR":"0","Pos":"T2","TPR":"-11","ID":"32102"},{"HSc":"4","Sks":[{"No":1,"ZID":1,"IsIn":false,"Y":457263.716,"X":2392389.453,"DTP":4281.3,"Dis":10998.2},{"No":2,"ZID":18,"IsIn":false,"Y":457457.737,"X":2392114.219,"DTP":345.1,"Dis":4041.0},{"No":3,"ZID":2,"IsIn":false,"Y":457454.259,"X":2392081.773,"DTP":58.3,"Dis":396.3},{"No":4,"ZID":0,"IsIn":true,"Y":457452.093,"X":2392086.312,"DTP":0,"Dis":58.3}],"HPR":"0","Pos":"T2","TPR":"-11","ID":"30911"},{"HSc":"4","Sks":[{"No":1,"ZID":4,"IsIn":false,"Y":457335.821,"X":2392438.147,"DTP":4444.5,"Dis":11068.1},{"No":2,"ZID":18,"IsIn":false,"Y":457470.59,"X":2392108.046,"DTP":345.9,"Dis":4278.9},{"No":3,"ZID":2,"IsIn":false,"Y":457452.191,"X":2392081.823,"DTP":51.8,"Dis":389.3},{"No":4,"ZID":0,"IsIn":true,"Y":457452.093,"X":2392086.312,"DTP":0,"Dis":51.8}],"HPR":"0","Pos":"T2","TPR":"-11","ID":"36689"},{"HSc":"5","Sks":[{"No":1,"ZID":1,"IsIn":false,"Y":457136.354,"X":2392512.904,"DTP":6366.6,"Dis":8913.3},{"No":2,"ZID":18,"IsIn":false,"Y":457467.04,"X":2392110.074,"DTP":340.3,"Dis":6254.5},{"No":3,"ZID":2,"IsIn":false,"Y":457447.327,"X":2392081.715,"DTP":77.4,"Dis":419.1},{"No":4,"ZID":2,"IsIn":false,"Y":457456.437,"X":2392089.019,"DTP":59.3,"Dis":140.1},{"No":5,"ZID":0,"IsIn":true,"Y":457452.093,"X":2392086.312,"DTP":0,"Dis":59.3}],"HPR":"1","Pos":"T24","TPR":"-3","ID":"25364"},{"HSc":"3","Sks":[{"No":1,"ZID":1,"IsIn":false,"Y":457204.465,"X":2392373.265,"DTP":4546.6,"Dis":10768.2},{"No":2,"ZID":2,"IsIn":false,"Y":457441.875,"X":2392095.525,"DTP":163.0,"Dis":4384.9},{"No":3,"ZID":0,"IsIn":true,"Y":457452.093,"X":2392086.312,"DTP":0,"Dis":163.0}],"HPR":"-1","Pos":"1","TPR":"-12","ID":"27644"}],"Te":{"Y":456734.818,"X":2393137.025},"Eag":0,"DBg":1,"Prs":48,"Fg":{"Y":457452.093,"X":2392086.312},"Avg":"4.162","Bir":5,"ID":4,"Bog":14}],"ID":3}]}