{"CrR":4,"Ps":[{"LN":"Varner","SN":"VARNER","Nat":"USA","IsA":false,"ID":"37189","FN":"Harold"},{"LN":"Pavon","SN":"PAVON","Nat":"FRA","IsA":false,"ID":"48153","FN":"Matthieu"},{"LN":"Putnam","SN":"PUTNAM","Nat":"USA","IsA":false,"ID":"28486","FN":"Michael"},{"LN":"Gregory","SN":"GREGORY","Nat":"ENG","IsA":false,"ID":"50735","FN":"Scott"},{"LN":"Zalatoris","SN":"ZALATORIS","Nat":"USA","IsA":false,"ID":"47483","FN":"Will"},{"LN":"Steele","SN":"STEELE","Nat":"USA","IsA":false,"ID":"29518","FN":"Brendan"},{"LN":"Hadley","SN":"HADLEY","Nat":"USA","IsA":false,"ID":"34563","FN":"Chesson"},{"LN":"Ellis","SN":"ELLIS","Nat":"ENG","IsA":true,"ID":"52569","FN":"Harry"},{"LN":"Vegas","SN":"VEGAS","Nat":"VEN","IsA":false,"ID":"27064","FN":"Jhonattan"},{"LN":"Frittelli","SN":"FRITTELLI","Nat":"RSA","IsA":false,"ID":"29970","FN":"Dylan"},{"LN":"Ghim","SN":"GHIM","Nat":"USA","IsA":true,"ID":"52375","FN":"Doug"},{"LN":"Oosthuizen","SN":"OOSTHUIZEN","Nat":"RSA","IsA":false,"ID":"26329","FN":"Louis"},{"LN":"Walker","SN":"WALKER","Nat":"USA","IsA":false,"ID":"25632","FN":"Jimmy"},{"LN":"Rose","SN":"ROSE","Nat":"ENG","IsA":false,"ID":"22405","FN":"Justin"},{"LN":"Watson","SN":"WATSON","Nat":"USA","IsA":false,"ID":"25804","FN":"Bubba"},{"LN":"Day","SN":"DAY","Nat":"AUS","IsA":false,"ID":"28089","FN":"Jason"},{"LN":"Koepka","SN":"KOEPKA","Nat":"USA","IsA":false,"ID":"36689","FN":"Brooks"},{"LN":"Hatton","SN":"HATTON","Nat":"ENG","IsA":false,"ID":"34363","FN":"Tyrrell"},{"LN":"Willett","SN":"WILLETT","Nat":"ENG","IsA":false,"ID":"32139","FN":"Danny"},{"LN":"Poulter","SN":"POULTER","Nat":"ENG","IsA":false,"ID":"24138","FN":"Ian"},{"LN":"Chappell","SN":"CHAPPELL","Nat":"USA","IsA":false,"ID":"32366","FN":"Kevin"},{"LN":"Johnston","SN":"JOHNSTON","Nat":"ENG","IsA":false,"ID":"34242","FN":"Andrew"},{"LN":"Berger","SN":"BERGER","Nat":"USA","IsA":false,"ID":"40026","FN":"Daniel"},{"LN":"DeChambeau","SN":"DECHAMBEAU","Nat":"USA","IsA":false,"ID":"47959","FN":"Bryson"},{"LN":"Fitzpatrick","SN":"FITZPATRICK","Nat":"ENG","IsA":false,"ID":"40098","FN":"Matthew"},{"LN":"Kuchar","SN":"KUCHAR","Nat":"USA","IsA":false,"ID":"23108","FN":"Matt"},{"LN":"Olesen","SN":"OLESEN","Nat":"DEN","IsA":false,"ID":"33968","FN":"Thorbjorn"},{"LN":"Sharma","SN":"SHARMA","Nat":"IND","IsA":false,"ID":"39113","FN":"Shubhankar"},{"LN":"Rodgers","SN":"RODGERS","Nat":"USA","IsA":false,"ID":"99160","FN":"Patrick"},{"LN":"Griffin","SN":"GRIFFIN","Nat":"USA","IsA":false,"ID":"35310","FN":"Lanto"},{"LN":"Lewis","SN":"LEWIS","Nat":"ENG","IsA":false,"ID":"35104","FN":"Tom"},{"LN":"Bergeron","SN":"BERGERON","Nat":"USA","IsA":true,"ID":"55411","FN":"Jacob"},{"LN":"Reitan","SN":"REITAN","Nat":"NOR","IsA":true,"ID":"49855","FN":"Kristoffer"},{"LN":"Gagne","SN":"GAGNE","Nat":"CRC","IsA":true,"ID":"55413","FN":"Luis"},{"LN":"Miller","SN":"MILLER C","Nat":"USA","IsA":false,"ID":"54596","FN":"Cole"},{"LN":"DeMorat","SN":"DEMORAT","Nat":"USA","IsA":false,"ID":"55412","FN":"Mickey"},{"LN":"Strafaci","SN":"STRAFACI","Nat":"USA","IsA":true,"ID":"54314","FN":"Tyler"},{"LN":"Hill","SN":"HILL","Nat":"SCO","IsA":false,"ID":"48126","FN":"Calum"},{"LN":"Stallings","SN":"STALLINGS","Nat":"USA","IsA":false,"ID":"30692","FN":"Scott"},{"LN":"Munoz","SN":"MUNOZ","Nat":"COL","IsA":false,"ID":"48822","FN":"Sebastian"},{"LN":"Southgate","SN":"SOUTHGATE","Nat":"ENG","IsA":false,"ID":"35174","FN":"Matthew"},{"LN":"Mullinax","SN":"MULLINAX","Nat":"USA","IsA":false,"ID":"46601","FN":"Trey"},{"LN":"Parziale","SN":"PARZIALE","Nat":"USA","IsA":true,"ID":"54318","FN":"Matt"},{"LN":"Scrivener","SN":"SCRIVENER","Nat":"AUS","IsA":false,"ID":"31569","FN":"Jason"},{"LN":"Bransdon","SN":"BRANSDON","Nat":"AUS","IsA":false,"ID":"20594","FN":"David"},{"LN":"Axley","SN":"AXLEY","Nat":"USA","IsA":false,"ID":"23048","FN":"Eric"},{"LN":"Duncan","SN":"DUNCAN","Nat":"USA","IsA":false,"ID":"45609","FN":"Tyler"},{"LN":"Rank","SN":"RANK","Nat":"CAN","IsA":true,"ID":"48095","FN":"Garrett"},{"LN":"Hughes","SN":"HUGHES","Nat":"CAN","IsA":false,"ID":"35506","FN":"Mackenzie"},{"LN":"Baddeley","SN":"BADDELEY","Nat":"AUS","IsA":false,"ID":"22371","FN":"Aaron"},{"LN":"Levy","SN":"LEVY","Nat":"FRA","IsA":false,"ID":"34579","FN":"Alexander"},{"LN":"Harman","SN":"HARMAN","Nat":"USA","IsA":false,"ID":"27644","FN":"Brian"},{"LN":"Cantlay","SN":"CANTLAY","Nat":"USA","IsA":false,"ID":"35450","FN":"Patrick"},{"LN":"Casey","SN":"CASEY","Nat":"ENG","IsA":false,"ID":"25364","FN":"Paul"},{"LN":"Kodaira","SN":"KODAIRA","Nat":"JPN","IsA":false,"ID":"32816","FN":"Satoshi"},{"LN":"Grace","SN":"GRACE","Nat":"RSA","IsA":false,"ID":"29974","FN":"Branden"},{"LN":"Johnson","SN":"JOHNSON Z","Nat":"USA","IsA":false,"ID":"24024","FN":"Zach"},{"LN":"Schwartzel","SN":"SCHWARTZEL","Nat":"RSA","IsA":false,"ID":"26331","FN":"Charl"},{"LN":"Reed","SN":"REED","Nat":"USA","IsA":false,"ID":"34360","FN":"Patrick"},{"LN":"McIlroy","SN":"MCILROY","Nat":"NIR","IsA":false,"ID":"28237","FN":"Rory"},{"LN":"Spieth","SN":"SPIETH","Nat":"USA","IsA":false,"ID":"34046","FN":"Jordan"},{"LN":"Mickelson","SN":"MICKELSON","Nat":"USA","IsA":false,"ID":"01810","FN":"Phil"},{"LN":"Matsuyama","SN":"MATSUYAMA","Nat":"JPN","IsA":false,"ID":"32839","FN":"Hideki"},{"LN":"Leishman","SN":"LEISHMAN","Nat":"AUS","IsA":false,"ID":"26851","FN":"Marc"},{"LN":"Fowler","SN":"FOWLER","Nat":"USA","IsA":false,"ID":"32102","FN":"Rickie"},{"LN":"Howell","SN":"HOWELL","Nat":"USA","IsA":false,"ID":"21961","FN":"Charles"},{"LN":"Haas","SN":"HAAS","Nat":"USA","IsA":false,"ID":"24924","FN":"Bill"},{"LN":"Hoffman","SN":"HOFFMAN","Nat":"USA","IsA":false,"ID":"12716","FN":"Charley"},{"LN":"Knox","SN":"KNOX","Nat":"SCO","IsA":false,"ID":"33122","FN":"Russell"},{"LN":"Wallace","SN":"WALLACE","Nat":"ENG","IsA":false,"ID":"48887","FN":"Matthew"},{"LN":"Ban","SN":"BAN","Nat":"USA","IsA":true,"ID":"55410","FN":"Shintaro"},{"LN":"Park","SN":"PARK","Nat":"KOR","IsA":false,"ID":"34130","FN":"Sung Joon"},{"LN":"Wilkinson","SN":"WILKINSON","Nat":"NZL","IsA":false,"ID":"25349","FN":"Tim"},{"LN":"Meyer","SN":"MEYER","Nat":"USA","IsA":false,"ID":"52330","FN":"Dylan"},{"LN":"Raza","SN":"RAZA","Nat":"USA","IsA":false,"ID":"51922","FN":"Sulman"},{"LN":"Naegel","SN":"NAEGEL","Nat":"USA","IsA":false,"ID":"39537","FN":"Chris"},{"LN":"Burns","SN":"BURNS","Nat":"USA","IsA":false,"ID":"99209","FN":"Sam"},{"LN":"Gay","SN":"GAY","Nat":"USA","IsA":false,"ID":"19846","FN":"Brian"},{"LN":"Burmester","SN":"BURMESTER","Nat":"RSA","IsA":false,"ID":"33974","FN":"Dean"},{"LN":"Yu","SN":"YU","Nat":"TPE","IsA":true,"ID":"99164","FN":"Chun An"},{"LN":"Liang","SN":"LIANG","Nat":"CHN","IsA":false,"ID":"24748","FN":"Wenchong"},{"LN":"Henley","SN":"HENLEY","Nat":"USA","IsA":false,"ID":"34098","FN":"Russell"},{"LN":"Wise","SN":"WISE","Nat":"USA","IsA":false,"ID":"99191","FN":"Aaron"},{"LN":"Uihlein","SN":"UIHLEIN","Nat":"USA","IsA":false,"ID":"29484","FN":"Peter"},{"LN":"Finau","SN":"FINAU","Nat":"USA","IsA":false,"ID":"29725","FN":"Tony"},{"LN":"List","SN":"LIST","Nat":"USA","IsA":false,"ID":"27129","FN":"Luke"},{"LN":"Woodland","SN":"WOODLAND","Nat":"USA","IsA":false,"ID":"31323","FN":"Gary"},{"LN":"Garcia","SN":"GARCIA","Nat":"ESP","IsA":false,"ID":"21209","FN":"Sergio"},{"LN":"Rahm","SN":"RAHM","Nat":"ESP","IsA":false,"ID":"46970","FN":"Jon"},{"LN":"Cabrera Bello","SN":"CABRERA BELLO","Nat":"ESP","IsA":false,"ID":"26499","FN":"Rafa"},{"LN":"Fleetwood","SN":"FLEETWOOD","Nat":"ENG","IsA":false,"ID":"30911","FN":"Tommy"},{"LN":"Molinari","SN":"MOLINARI","Nat":"ITA","IsA":false,"ID":"25198","FN":"Francesco"},{"LN":"Noren","SN":"NOREN","Nat":"SWE","IsA":false,"ID":"27349","FN":"Alex"},{"LN":"Smith","SN":"SMITH","Nat":"AUS","IsA":false,"ID":"35891","FN":"Cameron"},{"LN":"Stanley","SN":"STANLEY","Nat":"USA","IsA":false,"ID":"30110","FN":"Kyle"},{"LN":"Perez","SN":"PEREZ","Nat":"USA","IsA":false,"ID":"24361","FN":"Pat"},{"LN":"Thomas","SN":"THOMAS","Nat":"USA","IsA":false,"ID":"33448","FN":"Justin"},{"LN":"Johnson","SN":"JOHNSON D","Nat":"USA","IsA":false,"ID":"30925","FN":"Dustin"},{"LN":"Woods","SN":"WOODS","Nat":"USA","IsA":false,"ID":"08793","FN":"Tiger"},{"LN":"Li","SN":"LI","Nat":"CHN","IsA":false,"ID":"35296","FN":"Haotong"},{"LN":"Kim","SN":"KIM","Nat":"KOR","IsA":false,"ID":"37455","FN":"Si Woo"},{"LN":"Aphibarnrat","SN":"APHIBARNRAT","Nat":"THA","IsA":false,"ID":"99190","FN":"Kiradech"},{"LN":"Dufner","SN":"DUFNER","Nat":"USA","IsA":false,"ID":"25686","FN":"Jason"},{"LN":"Thornberry","SN":"THORNBERRY","Nat":"USA","IsA":true,"ID":"52144","FN":"Braden"},{"LN":"Snedeker","SN":"SNEDEKER","Nat":"USA","IsA":false,"ID":"27649","FN":"Brandt"},{"LN":"Lumsden","SN":"LUMSDEN","Nat":"SCO","IsA":true,"ID":"55415","FN":"Ryan"},{"LN":"Morrison","SN":"MORRISON","Nat":"ENG","IsA":false,"ID":"29256","FN":"James"},{"LN":"Wilson","SN":"WILSON","Nat":"USA","IsA":false,"ID":"36685","FN":"Cameron"},{"LN":"Grimmer","SN":"GRIMMER","Nat":"USA","IsA":true,"ID":"46439","FN":"Will"},{"LN":"Barbaree","SN":"BARBAREE","Nat":"USA","IsA":true,"ID":"50157","FN":"Philip"},{"LN":"Rasmussen","SN":"RASMUSSEN","Nat":"USA","IsA":true,"ID":"55416","FN":"Rhett"},{"LN":"Hebert","SN":"HEBERT","Nat":"USA","IsA":false,"ID":"45535","FN":"Michael"},{"LN":"Block","SN":"BLOCK","Nat":"USA","IsA":false,"ID":"22764","FN":"Michael"},{"LN":"Jones","SN":"JONES","Nat":"AUS","IsA":false,"ID":"26300","FN":"Matthew"},{"LN":"Fox","SN":"FOX","Nat":"NZL","IsA":false,"ID":"29936","FN":"Ryan"},{"LN":"Akiyoshi","SN":"AKIYOSHI","Nat":"JPN","IsA":false,"ID":"32813","FN":"Shota"},{"LN":"Waring","SN":"WARING","Nat":"ENG","IsA":false,"ID":"31113","FN":"Paul"},{"LN":"Humphrey","SN":"HUMPHREY","Nat":"USA","IsA":true,"ID":"54901","FN":"Theo"},{"LN":"Werenski","SN":"WERENSKI","Nat":"USA","IsA":false,"ID":"47128","FN":"Richy"},{"LN":"Castro","SN":"CASTRO","Nat":"USA","IsA":false,"ID":"32200","FN":"Roberto"},{"LN":"Schniederjans","SN":"SCHNIEDRJNS","Nat":"USA","IsA":false,"ID":"46501","FN":"Ollie"},{"LN":"Goodwin","SN":"GOODWIN","Nat":"USA","IsA":true,"ID":"55165","FN":"Noah"},{"LN":"Ramsay","SN":"RAMSAY","Nat":"SCO","IsA":false,"ID":"29531","FN":"Richie"},{"LN":"Perry","SN":"PERRY","Nat":"USA","IsA":false,"ID":"01945","FN":"Kenny"},{"LN":"Bradley","SN":"BRADLEY","Nat":"USA","IsA":false,"ID":"33141","FN":"Keegan"},{"LN":"Schauffele","SN":"SCHAUFFELE","Nat":"USA","IsA":false,"ID":"48081","FN":"Xander"},{"LN":"Glover","SN":"GLOVER","Nat":"USA","IsA":false,"ID":"25900","FN":"Lucas"},{"LN":"Simpson","SN":"SIMPSON","Nat":"USA","IsA":false,"ID":"29221","FN":"Webb"},{"LN":"McDowell","SN":"MCDOWELL","Nat":"NIR","IsA":false,"ID":"25572","FN":"Graeme"},{"LN":"Els","SN":"ELS","Nat":"RSA","IsA":false,"ID":"06522","FN":"Ernie"},{"LN":"Stricker","SN":"STRICKER","Nat":"USA","IsA":false,"ID":"06527","FN":"Steve"},{"LN":"Furyk","SN":"FURYK","Nat":"USA","IsA":false,"ID":"10809","FN":"Jim"},{"LN":"Stenson","SN":"STENSON","Nat":"SWE","IsA":false,"ID":"21528","FN":"Henrik"},{"LN":"Scott","SN":"SCOTT","Nat":"AUS","IsA":false,"ID":"24502","FN":"Adam"},{"LN":"Kaymer","SN":"KAYMER","Nat":"GER","IsA":false,"ID":"27408","FN":"Martin"},{"LN":"Kisner","SN":"KISNER","Nat":"USA","IsA":false,"ID":"29478","FN":"Kevin"},{"LN":"Fisher","SN":"FISHER","Nat":"ENG","IsA":false,"ID":"27896","FN":"Ross"},{"LN":"Hadwin","SN":"HADWIN","Nat":"CAN","IsA":false,"ID":"33399","FN":"Adam"},{"LN":"Lowry","SN":"LOWRY","Nat":"IRL","IsA":false,"ID":"33204","FN":"Shane"},{"LN":"Reavie","SN":"REAVIE","Nat":"USA","IsA":false,"ID":"26476","FN":"Chez"},{"LN":"Herbert","SN":"HERBERT","Nat":"AUS","IsA":false,"ID":"39058","FN":"Lucas"},{"LN":"Stuard","SN":"STUARD","Nat":"USA","IsA":false,"ID":"31560","FN":"Brian"},{"LN":"Hagestad","SN":"HAGESTAD","Nat":"USA","IsA":true,"ID":"51586","FN":"Stewart"},{"LN":"Huang","SN":"HUANG","Nat":"USA","IsA":true,"ID":"55414","FN":"Franklin"},{"LN":"Vazquez","SN":"VAZQUEZ","Nat":"MEX","IsA":false,"ID":"35469","FN":"Sebastian"},{"LN":"Miller","SN":"MILLER M","Nat":"USA","IsA":false,"ID":"99168","FN":"Michael"},{"LN":"Babcock","SN":"BABCOCK","Nat":"USA","IsA":false,"ID":"51691","FN":"Christopher"},{"LN":"Wiseman","SN":"WISEMAN","Nat":"USA","IsA":true,"ID":"55417","FN":"Timothy"},{"LN":"Gazzolo","SN":"GAZZOLO","Nat":"USA","IsA":false,"ID":"49310","FN":"David"},{"LN":"Im","SN":"IM","Nat":"KOR","IsA":false,"ID":"39971","FN":"Sungjae"},{"LN":"Piercy","SN":"PIERCY","Nat":"USA","IsA":false,"ID":"25818","FN":"Scott"},{"LN":"Evans","SN":"EVANS","Nat":"ENG","IsA":false,"ID":"46907","FN":"Ryan"},{"LN":"Hoshino","SN":"HOSHINO","Nat":"JPN","IsA":false,"ID":"47056","FN":"Rikuya"},{"LN":"Potter","SN":"POTTER JR","Nat":"USA","IsA":false,"ID":"27556","FN":"Ted"},{"LN":"Grillo","SN":"GRILLO","Nat":"ARG","IsA":false,"ID":"31646","FN":"Emiliano"},{"LN":"An","SN":"AN","Nat":"KOR","IsA":false,"ID":"33948","FN":"Byeong Hun"}],"Fed":"BallPlots","Rs":[{"Hs":[{"Rnk":"16","Par":4,"HY":465,"HPs":[{"HSc":"5","Sks":[{"No":1,"ZID":1,"IsIn":false,"Y":269602.797,"X":1416883.713,"DTP":6557.0,"Dis":9910.6},{"No":2,"ZID":1,"IsIn":false,"Y":270205.938,"X":1416841.854,"DTP":777.5,"Dis":7257.0},{"No":3,"ZID":1,"IsIn":false,"Y":270105.506,"X":1416816.568,"DTP":477.0,"Dis":1243.3},{"No":4,"ZID":2,"IsIn":false,"Y":270143.836,"X":1416817.012,"DTP":23.1,"Dis":460.7},{"No":5,"ZID":0,"IsIn":true,"Y":270145.328,"X":1416818.488,"DTP":0,"Dis":23.1}],"HPR":"1","Pos":"T48","TPR":"16","ID":"25349"},{"HSc":"4","Sks":[{"No":1,"ZID":20,"IsIn":false,"Y":269581.417,"X":1416821.931,"DTP":6765.4,"Dis":9817.9},{"No":2,"ZID":1,"IsIn":false,"Y":270111.976,"X":1416791.648,"DTP":512.0,"Dis":6377.3},{"No":3,"ZID":2,"IsIn":false,"Y":270144.65,"X":1416817.567,"DTP":11.6,"Dis":500.9},{"No":4,"ZID":0,"IsIn":true,"Y":270145.328,"X":1416818.488,"DTP":0,"Dis":11.6}],"HPR":"0","Pos":"T36","TPR":"13","ID":"24924"},{"HSc":"4","Sks":[{"No":1,"ZID":1,"IsIn":false,"Y":269686.853,"X":1416879.199,"DTP":5549.6,"Dis":10912.7},{"No":2,"ZID":2,"IsIn":false,"Y":270191.949,"X":1416782.716,"DTP":703.2,"Dis":6172.9},{"No":3,"ZID":2,"IsIn":false,"Y":270148.997,"X":1416818.208,"DTP":42.1,"Dis":668.8},{"No":4,"ZID":0,"IsIn":true,"Y":270145.328,"X":1416818.488,"DTP":0,"Dis":42.1}],"HPR":"0","Pos":"T41","TPR":"14","ID":"27064"},{"HSc":"5","Sks":[{"No":1,"ZID":4,"IsIn":false,"Y":269620.054,"X":1416940.668,"DTP":6469.6,"Dis":10014.7},{"No":2,"ZID":20,"IsIn":false,"Y":270127.607,"X":1416723.096,"DTP":1162.5,"Dis":6627.0},{"No":3,"ZID":2,"IsIn":false,"Y":270130.874,"X":1416815.773,"DTP":174.5,"Dis":1113.3},{"No":4,"ZID":2,"IsIn":false,"Y":270146.631,"X":1416818.382,"DTP":13.6,"Dis":191.7},{"No":5,"ZID":0,"IsIn":true,"Y":270145.328,"X":1416818.488,"DTP":0,"Dis":13.6}],"HPR":"1","Pos":"64","TPR":"21","ID":"36685"},{"HSc":"5","Sks":[{"No":1,"ZID":1,"IsIn":false,"Y":269653.776,"X":1416876.854,"DTP":5939.9,"Dis":10526.8},{"No":2,"ZID":1,"IsIn":false,"Y":270107.906,"X":1416834.946,"DTP":488.9,"Dis":5474.3},{"No":3,"ZID":2,"IsIn":false,"Y":270148.237,"X":1416814.988,"DTP":52.5,"Dis":540.4},{"No":4,"ZID":2,"IsIn":false,"Y":270142.669,"X":1416820.833,"DTP":40.4,"Dis":96.9},{"No":5,"ZID":0,"IsIn":true,"Y":270145.328,"X":1416818.488,"DTP":0,"Dis":40.4}],"HPR":"1","Pos":"T25","TPR":"12","ID":"48153"},{"HSc":"4","Sks":[{"No":1,"ZID":20,"IsIn":false,"Y":269554.379,"X":1416820.059,"DTP":7089.6,"Dis":9510.2},{"No":2,"ZID":18,"IsIn":false,"Y":270011.631,"X":1416727.582,"DTP":1938.6,"Dis":5598.1},{"No":3,"ZID":2,"IsIn":false,"Y":270146.506,"X":1416822.563,"DTP":48.8,"Dis":1980.1},{"No":4,"ZID":0,"IsIn":true,"Y":270145.328,"X":1416818.488,"DTP":0,"Dis":48.8}],"HPR":"0","Pos":"T48","TPR":"16","ID":"27649"},{"HSc":"3","Sks":[{"No":1,"ZID":1,"IsIn":false,"Y":269647.18,"X":1416875.935,"DTP":6017.2,"Dis":10450.8},{"No":2,"ZID":2,"IsIn":false,"Y":270135.527,"X":1416818.478,"DTP":115.6,"Dis":5902.5},{"No":3,"ZID":0,"IsIn":true,"Y":270145.328,"X":1416818.488,"DTP":0,"Dis":115.6}],"HPR":"-1","Pos":"15","TPR":"9","ID":"99190"},{"HSc":"4","Sks":[{"No":1,"ZID":1,"IsIn":false,"Y":269619.551,"X":1416876.959,"DTP":6347.7,"Dis":10122.3},{"No":2,"ZID":1,"IsIn":false,"Y":270113.717,"X":1416823.845,"DTP":383.2,"Dis":5965.4},{"No":3,"ZID":2,"IsIn":false,"Y":270146.942,"X":1416816.856,"DTP":25.4,"Dis":408.0},{"No":4,"ZID":0,"IsIn":true,"Y":270145.328,"X":1416818.488,"DTP":0,"Dis":25.4}],"HPR":"0","Pos":"T20","TPR":"11","ID":"06527"},{"HSc":"4","Sks":[{"No":1,"ZID":20,"IsIn":false,"Y":269612.01,"X":1416819.82,"DTP":6398.3,"Dis":10179.8},{"No":2,"ZID":2,"IsIn":false,"Y":270134.346,"X":1416833.803,"DTP":224.1,"Dis":6270.8},{"No":3,"ZID":2,"IsIn":false,"Y":270144.338,"X":1416816.99,"DTP":19.4,"Dis":234.7},{"No":4,"ZID":0,"IsIn":true,"Y":270145.328,"X":1416818.488,"DTP":0,"Dis":19.4}],"HPR":"0","Pos":"T36","TPR":"13","ID":"31323"},{"HSc":"4","Sks":[{"No":1,"ZID":1,"IsIn":false,"Y":269694.4,"X":1416883.61,"DTP":5467.1,"Dis":10993.3},{"No":2,"ZID":2,"IsIn":false,"Y":270142.827,"X":1416800.576,"DTP":214.9,"Dis":5474.6},{"No":3,"ZID":2,"IsIn":false,"Y":270141.146,"X":1416821.191,"DTP":57.7,"Dis":248.2},{"No":4,"ZID":0,"IsIn":true,"Y":270145.328,"X":1416818.488,"DTP":0,"Dis":57.7}],"HPR":"0","Pos":"T56","TPR":"17","ID":"33974"},{"HSc":"4","Sks":[{"No":1,"ZID":1,"IsIn":false,"Y":269655.372,"X":1416876.844,"DTP":5920.9,"Dis":10545.6},{"No":2,"ZID":2,"IsIn":false,"Y":270123.253,"X":1416838.416,"DTP":354.8,"Dis":5635.4},{"No":3,"ZID":2,"IsIn":false,"Y":270148.243,"X":1416816.401,"DTP":40.9,"Dis":399.7},{"No":4,"ZID":0,"IsIn":true,"Y":270145.328,"X":1416818.488,"DTP":0,"Dis":40.9}],"HPR":"0","Pos":"T48","TPR":"16","ID":"55413"},{"HSc":"4","Sks":[{"No":1,"ZID":1,"IsIn":false,"Y":269677.574,"X":1416858.736,"DTP":5633.5,"Dis":10846.7},{"No":2,"ZID":2,"IsIn":false,"Y":270133.89,"X":1416799.242,"DTP":266.6,"Dis":5523.9},{"No":3,"ZID":2,"IsIn":false,"Y":270146.42,"X":1416820.578,"DTP":26.2,"Dis":296.9},{"No":4,"ZID":0,"IsIn":true,"Y":270145.328,"X":1416818.488,"DTP":0,"Dis":26.2}],"HPR":"0","Pos":"65","TPR":"22","ID":"32366"},{"HSc":"3","Sks":[{"No":1,"ZID":1,"IsIn":false,"Y":269658.506,"X":1416878.804,"DTP":5886.4,"Dis":10578.6},{"No":2,"ZID":2,"IsIn":false,"Y":270146.169,"X":1416812.592,"DTP":69.4,"Dis":5907.6},{"No":3,"ZID":0,"IsIn":true,"Y":270145.328,"X":1416818.488,"DTP":0,"Dis":69.4}],"HPR":"-1","Pos":"T6","TPR":"6","ID":"40026"},{"HSc":"6","Sks":[{"No":1,"ZID":4,"IsIn":false,"Y":269618.632,"X":1416799.884,"DTP":6322.8,"Dis":10318.4},{"No":2,"ZID":4,"IsIn":false,"Y":269623.938,"X":1416783.623,"DTP":6269.5,"Dis":206.2},{"No":3,"ZID":4,"IsIn":false,"Y":269654.288,"X":1416804.455,"DTP":5894.3,"Dis":442.3},{"No":4,"ZID":2,"IsIn":false,"Y":270141.161,"X":1416825.91,"DTP":100.0,"Dis":5849.7},{"No":5,"ZID":2,"IsIn":false,"Y":270144.948,"X":1416815.88,"DTP":29.5,"Dis":128.7},{"No":6,"ZID":0,"IsIn":true,"Y":270145.328,"X":1416818.488,"DTP":0,"Dis":29.5}],"HPR":"2","Pos":"67","TPR":"26","ID":"33948"},{"HSc":"4","Sks":[{"No":1,"ZID":1,"IsIn":false,"Y":269704.268,"X":1416870.943,"DTP":5329.8,"Dis":11135.1},{"No":2,"ZID":2,"IsIn":false,"Y":270168.607,"X":1416820.568,"DTP":278.4,"Dis":5606.7},{"No":3,"ZID":2,"IsIn":false,"Y":270141.758,"X":1416818.285,"DTP":40.8,"Dis":323.4},{"No":4,"ZID":0,"IsIn":true,"Y":270145.328,"X":1416818.488,"DTP":0,"Dis":40.8}],"HPR":"0","Pos":"T48","TPR":"16","ID":"54318"},{"HSc":"3","Sks":[{"No":1,"ZID":1,"IsIn":false,"Y":269699.305,"X":1416876.174,"DTP":5396.6,"Dis":11065.8},{"No":2,"ZID":2,"IsIn":false,"Y":270129.995,"X":1416783.3,"DTP":458.6,"Dis":5288.8},{"No":3,"ZID":0,"IsIn":true,"Y":270145.328,"X":1416818.488,"DTP":0,"Dis":458.6}],"HPR":"-1","Pos":"T48","TPR":"16","ID":"27896"},{"HSc":"5","Sks":[{"No":1,"ZID":20,"IsIn":false,"Y":269603.302,"X":1416813.048,"DTP":6503.0,"Dis":10099.1},{"No":2,"ZID":20,"IsIn":false,"Y":269758.327,"X":1416808.132,"DTP":4644.2,"Dis":1861.2},{"No":3,"ZID":1,"IsIn":false,"Y":270104.906,"X":1416833.81,"DTP":517.1,"Dis":4170.7},{"No":4,"ZID":2,"IsIn":false,"Y":270147.821,"X":1416819.089,"DTP":28.7,"Dis":544.9},{"No":5,"ZID":0,"IsIn":true,"Y":270145.328,"X":1416818.488,"DTP":0,"Dis":28.7}],"HPR":"1","Pos":"T16","TPR":"10","ID":"35296"},{"HSc":"4","Sks":[{"No":1,"ZID":1,"IsIn":false,"Y":269622.605,"X":1416866.234,"DTP":6298.2,"Dis":10182.3},{"No":2,"ZID":2,"IsIn":false,"Y":270140.758,"X":1416834.0,"DTP":192.0,"Dis":6231.4},{"No":3,"ZID":2,"IsIn":false,"Y":270144.088,"X":1416814.755,"DTP":45.1,"Dis":234.4},{"No":4,"ZID":0,"IsIn":true,"Y":270145.328,"X":1416818.488,"DTP":0,"Dis":45.1}],"HPR":"0","Pos":"T25","TPR":"12","ID":"25198"},{"HSc":"4","Sks":[{"No":1,"ZID":1,"IsIn":false,"Y":269677.885,"X":1416874.633,"DTP":5649.6,"Dis":10816.1},{"No":2,"ZID":2,"IsIn":false,"Y":270140.737,"X":1416825.572,"DTP":99.2,"Dis":5587.4},{"No":3,"ZID":2,"IsIn":false,"Y":270146.457,"X":1416817.991,"DTP":12.7,"Dis":114.0},{"No":4,"ZID":0,"IsIn":true,"Y":270145.328,"X":1416818.488,"DTP":0,"Dis":12.7}],"HPR":"0","Pos":"T10","TPR":"7","ID":"29221"},{"HSc":"4","Sks":[{"No":1,"ZID":4,"IsIn":false,"Y":269650.068,"X":1416730.492,"DTP":6036.4,"Dis":10929.7},{"No":2,"ZID":2,"IsIn":false,"Y":270173.583,"X":1416783.846,"DTP":534.5,"Dis":6317.2},{"No":3,"ZID":2,"IsIn":false,"Y":270135.157,"X":1416823.647,"DTP":134.8,"Dis":664.0},{"No":4,"ZID":0,"IsIn":true,"Y":270145.328,"X":1416818.488,"DTP":0,"Dis":134.8}],"HPR":"0","Pos":"T48","TPR":"16","ID":"29484"},{"HSc":"3","Sks":[{"No":1,"ZID":1,"IsIn":false,"Y":269660.149,"X":1416879.315,"DTP":5867.6,"Dis":10596.9},{"No":2,"ZID":2,"IsIn":false,"Y":270144.621,"X":1416817.325,"DTP":14.2,"Dis":5863.0},{"No":3,"ZID":0,"IsIn":true,"Y":270145.328,"X":1416818.488,"DTP":0,"Dis":14.2}],"HPR":"-1","Pos":"5","TPR":"5","ID":"29725"},{"HSc":"4","Sks":[{"No":1,"ZID":1,"IsIn":false,"Y":269679.95,"X":1416864.563,"DTP":5611.6,"Dis":10861.8},{"No":2,"ZID":6,"IsIn":false,"Y":270118.505,"X":1416828.446,"DTP":341.6,"Dis":5282.1},{"No":3,"ZID":2,"IsIn":false,"Y":270147.985,"X":1416816.318,"DTP":39.1,"Dis":382.8},{"No":4,"ZID":0,"IsIn":true,"Y":270145.328,"X":1416818.488,"DTP":0,"Dis":39.1}],"HPR":"0","Pos":"T20","TPR":"11","ID":"19846"},{"HSc":"3","Sks":[{"No":1,"ZID":1,"IsIn":false,"Y":269735.061,"X":1416873.392,"DTP":4966.4,"Dis":11493.7},{"No":2,"ZID":2,"IsIn":false,"Y":270150.597,"X":1416814.777,"DTP":75.3,"Dis":5037.3},{"No":3,"ZID":0,"IsIn":true,"Y":270145.328,"X":1416818.488,"DTP":0,"Dis":75.3}],"HPR":"-1","Pos":"T41","TPR":"14","ID":"99209"},{"HSc":"4","Sks":[{"No":1,"ZID":1,"IsIn":false,"Y":269749.822,"X":1416867.79,"DTP":4781.9,"Dis":11679.1},{"No":2,"ZID":2,"IsIn":false,"Y":270178.164,"X":1416825.659,"DTP":401.3,"Dis":5166.2},{"No":3,"ZID":2,"IsIn":false,"Y":270142.898,"X":1416818.3,"DTP":27.2,"Dis":432.4},{"No":4,"ZID":0,"IsIn":true,"Y":270145.328,"X":1416818.488,"DTP":0,"Dis":27.2}],"HPR":"0","Pos":"T56","TPR":"17","ID":"39537"},{"HSc":"4","Sks":[{"No":1,"ZID":1,"IsIn":false,"Y":269648.03,"X":1416873.638,"DTP":6004.0,"Dis":10465.8},{"No":2,"ZID":2,"IsIn":false,"Y":270161.848,"X":1416827.494,"DTP":223.7,"Dis":6192.6},{"No":3,"ZID":2,"IsIn":false,"Y":270141.197,"X":1416817.306,"DTP":49.5,"Dis":276.4},{"No":4,"ZID":0,"IsIn":true,"Y":270145.328,"X":1416818.488,"DTP":0,"Dis":49.5}],"HPR":"0","Pos":"T20","TPR":"11","ID":"52330"},{"HSc":"4","Sks":[{"No":1,"ZID":1,"IsIn":false,"Y":269601.648,"X":1416877.854,"DTP":6562.2,"Dis":9909.0},{"No":2,"ZID":2,"IsIn":false,"Y":270159.426,"X":1416820.637,"DTP":169.1,"Dis":6729.9},{"No":3,"ZID":2,"IsIn":false,"Y":270141.706,"X":1416818.602,"DTP":41.4,"Dis":214.1},{"No":4,"ZID":0,"IsIn":true,"Y":270145.328,"X":1416818.488,"DTP":0,"Dis":41.4}],"HPR":"0","Pos":"T48","TPR":"16","ID":"01810"},{"HSc":"6","Sks":[{"No":1,"ZID":1,"IsIn":false,"Y":269701.692,"X":1416851.309,"DTP":5337.7,"Dis":11147.3},{"No":2,"ZID":1,"IsIn":false,"Y":270193.085,"X":1416867.732,"DTP":821.1,"Dis":5901.5},{"No":3,"ZID":1,"IsIn":false,"Y":270107.494,"X":1416816.764,"DTP":453.1,"Dis":1195.7},{"No":4,"ZID":2,"IsIn":false,"Y":270151.201,"X":1416820.076,"DTP":70.9,"Dis":526.7},{"No":5,"ZID":2,"IsIn":false,"Y":270141.691,"X":1416820.811,"DTP":49.7,"Dis":114.5},{"No":6,"ZID":0,"IsIn":true,"Y":270145.328,"X":1416818.488,"DTP":0,"Dis":49.7}],"HPR":"2","Pos":"62","TPR":"19","ID":"34242"},{"HSc":"3","Sks":[{"No":1,"ZID":1,"IsIn":false,"Y":269698.833,"X":1416872.41,"DTP":5396.6,"Dis":11067.9},{"No":2,"ZID":2,"IsIn":false,"Y":270166.404,"X":1416816.762,"DTP":251.7,"Dis":5652.4},{"No":3,"ZID":0,"IsIn":true,"Y":270145.328,"X":1416818.488,"DTP":0,"Dis":251.7}],"HPR":"-1","Pos":"T12","TPR":"8","ID":"24024"},{"HSc":"4","Sks":[{"No":1,"ZID":1,"IsIn":false,"Y":269648.029,"X":1416880.273,"DTP":6013.3,"Dis":10451.8},{"No":2,"ZID":2,"IsIn":false,"Y":270145.542,"X":1416831.498,"DTP":154.0,"Dis":6000.7},{"No":3,"ZID":2,"IsIn":false,"Y":270145.391,"X":1416816.654,"DTP":19.9,"Dis":178.1},{"No":4,"ZID":0,"IsIn":true,"Y":270145.328,"X":1416818.488,"DTP":0,"Dis":19.9}],"HPR":"0","Pos":"T16","TPR":"10","ID":"25364"},{"HSc":"4","Sks":[{"No":1,"ZID":1,"IsIn":false,"Y":269829.033,"X":1416835.792,"DTP":3800.6,"Dis":12682.0},{"No":2,"ZID":2,"IsIn":false,"Y":270132.021,"X":1416820.161,"DTP":158.9,"Dis":3642.2},{"No":3,"ZID":2,"IsIn":false,"Y":270148.436,"X":1416818.514,"DTP":35.2,"Dis":198.0},{"No":4,"ZID":0,"IsIn":true,"Y":270145.328,"X":1416818.488,"DTP":0,"Dis":35.2}],"HPR":"0","Pos":"T16","TPR":"10","ID":"26329"},{"HSc":"3","Sks":[{"No":1,"ZID":4,"IsIn":false,"Y":269666.453,"X":1416800.754,"DTP":5750.0,"Dis":10870.9},{"No":2,"ZID":2,"IsIn":false,"Y":270162.26,"X":1416819.542,"DTP":201.5,"Dis":5955.7},{"No":3,"ZID":0,"IsIn":true,"Y":270145.328,"X":1416818.488,"DTP":0,"Dis":201.5}],"HPR":"-1","Pos":"T45","TPR":"15","ID":"35450"},{"HSc":"4","Sks":[{"No":1,"ZID":1,"IsIn":false,"Y":269711.96,"X":1416867.324,"DTP":5233.0,"Dis":11233.3},{"No":2,"ZID":2,"IsIn":false,"Y":270155.286,"X":1416833.31,"DTP":212.2,"Dis":5337.4},{"No":3,"ZID":2,"IsIn":false,"Y":270141.974,"X":1416815.972,"DTP":48.2,"Dis":262.3},{"No":4,"ZID":0,"IsIn":true,"Y":270145.328,"X":1416818.488,"DTP":0,"Dis":48.2}],"HPR":"0","Pos":"T25","TPR":"12","ID":"22371"},{"HSc":"4","Sks":[{"No":1,"ZID":1,"IsIn":false,"Y":269751.155,"X":1416840.219,"DTP":4736.2,"Dis":11754.3},{"No":2,"ZID":2,"IsIn":false,"Y":270147.791,"X":1416832.665,"DTP":170.6,"Dis":4761.6},{"No":3,"ZID":2,"IsIn":false,"Y":270145.603,"X":1416815.892,"DTP":29.2,"Dis":203.0},{"No":4,"ZID":0,"IsIn":true,"Y":270145.328,"X":1416818.488,"DTP":0,"Dis":29.2}],"HPR":"0","Pos":"T6","TPR":"6","ID":"48081"},{"HSc":"4","Sks":[{"No":1,"ZID":1,"IsIn":false,"Y":269770.816,"X":1416889.361,"DTP":4573.6,"Dis":11888.4},{"No":2,"ZID":6,"IsIn":false,"Y":270131.055,"X":1416852.179,"DTP":437.0,"Dis":4347.8},{"No":3,"ZID":2,"IsIn":false,"Y":270145.42,"X":1416815.486,"DTP":33.9,"Dis":472.9},{"No":4,"ZID":0,"IsIn":true,"Y":270145.328,"X":1416818.488,"DTP":0,"Dis":33.9}],"HPR":"0","Pos":"T16","TPR":"10","ID":"32839"},{"HSc":"4","Sks":[{"No":1,"ZID":1,"IsIn":false,"Y":269713.19,"X":1416877.207,"DTP":5232.9,"Dis":11227.8},{"No":2,"ZID":1,"IsIn":false,"Y":270106.817,"X":1416816.346,"DTP":461.4,"Dis":4780.9},{"No":3,"ZID":2,"IsIn":false,"Y":270149.969,"X":1416819.171,"DTP":54.2,"Dis":519.6},{"No":4,"ZID":0,"IsIn":true,"Y":270145.328,"X":1416818.488,"DTP":0,"Dis":54.2}],"HPR":"0","Pos":"T25","TPR":"12","ID":"47959"},{"HSc":"4","Sks":[{"No":1,"ZID":1,"IsIn":false,"Y":269759.78,"X":1416881.539,"DTP":4687.3,"Dis":11770.9},{"No":2,"ZID":2,"IsIn":false,"Y":270143.705,"X":1416833.556,"DTP":179.8,"Dis":4644.4},{"No":3,"ZID":2,"IsIn":false,"Y":270145.594,"X":1416816.022,"DTP":27.7,"Dis":211.6},{"No":4,"ZID":0,"IsIn":true,"Y":270145.328,"X":1416818.488,"DTP":0,"Dis":27.7}],"HPR":"0","Pos":"4","TPR":"4","ID":"34360"},{"HSc":"3","Sks":[{"No":1,"ZID":1,"IsIn":false,"Y":269830.322,"X":1416891.4,"DTP":3880.5,"Dis":12592.5},{"No":2,"ZID":2,"IsIn":false,"Y":270183.948,"X":1416821.471,"DTP":462.8,"Dis":4328.3},{"No":3,"ZID":0,"IsIn":true,"Y":270145.328,"X":1416818.488,"DTP":0,"Dis":462.8}],"HPR":"-1","Pos":"T6","TPR":"6","ID":"34363"},{"HSc":"4","Sks":[{"No":1,"ZID":20,"IsIn":false,"Y":269675.221,"X":1416911.002,"DTP":5748.9,"Dis":10717.0},{"No":2,"ZID":1,"IsIn":false,"Y":270110.303,"X":1416811.796,"DTP":426.5,"Dis":5356.1},{"No":3,"ZID":2,"IsIn":false,"Y":270143.227,"X":1416820.075,"DTP":29.5,"Dis":408.1},{"No":4,"ZID":0,"IsIn":true,"Y":270145.328,"X":1416818.488,"DTP":0,"Dis":29.5}],"HPR":"0","Pos":"T56","TPR":"17","ID":"25632"},{"HSc":"4","Sks":[{"No":1,"ZID":1,"IsIn":false,"Y":269740.596,"X":1416873.017,"DTP":4899.9,"Dis":11559.8},{"No":2,"ZID":2,"IsIn":false,"Y":270189.592,"X":1416829.384,"DTP":545.0,"Dis":5414.8},{"No":3,"ZID":2,"IsIn":false,"Y":270141.194,"X":1416818.993,"DTP":47.9,"Dis":594.1},{"No":4,"ZID":0,"IsIn":true,"Y":270145.328,"X":1416818.488,"DTP":0,"Dis":47.9}],"HPR":"0","Pos":"T25","TPR":"12","ID":"29974"},{"HSc":"5","Sks":[{"No":1,"ZID":1,"IsIn":false,"Y":269659.833,"X":1416869.541,"DTP":5858.0,"Dis":10613.9},{"No":2,"ZID":6,"IsIn":false,"Y":270164.782,"X":1416858.708,"DTP":534.0,"Dis":6062.8},{"No":3,"ZID":2,"IsIn":false,"Y":270140.709,"X":1416817.082,"DTP":55.8,"Dis":577.0},{"No":4,"ZID":2,"IsIn":false,"Y":270148.162,"X":1416818.982,"DTP":32.4,"Dis":92.3},{"No":5,"ZID":0,"IsIn":true,"Y":270145.328,"X":1416818.488,"DTP":0,"Dis":32.4}],"HPR":"1","Pos":"63","TPR":"20","ID":"29518"},{"HSc":"5","Sks":[{"No":1,"ZID":4,"IsIn":false,"Y":269611.052,"X":1416939.505,"DTP":6571.8,"Dis":9908.8},{"No":2,"ZID":1,"IsIn":false,"Y":269967.848,"X":1416835.507,"DTP":2138.7,"Dis":4459.8},{"No":3,"ZID":2,"IsIn":false,"Y":270165.524,"X":1416821.185,"DTP":242.4,"Dis":2379.6},{"No":4,"ZID":2,"IsIn":false,"Y":270143.588,"X":1416818.929,"DTP":19.4,"Dis":264.7},{"No":5,"ZID":0,"IsIn":true,"Y":270145.328,"X":1416818.488,"DTP":0,"Dis":19.4}],"HPR":"1","Pos":"66","TPR":"23","ID":"46439"},{"HSc":"4","Sks":[{"No":1,"ZID":1,"IsIn":false,"Y":269715.643,"X":1416849.611,"DTP":5169.1,"Dis":11315.3},{"No":2,"ZID":6,"IsIn":false,"Y":270198.733,"X":1416844.178,"DTP":709.1,"Dis":5798.9},{"No":3,"ZID":2,"IsIn":false,"Y":270145.274,"X":1416820.35,"DTP":20.3,"Dis":702.4},{"No":4,"ZID":0,"IsIn":true,"Y":270145.328,"X":1416818.488,"DTP":0,"Dis":20.3}],"HPR":"0","Pos":"T41","TPR":"14","ID":"29936"},{"HSc":"7","Sks":[{"No":1,"ZID":1,"IsIn":false,"Y":269725.566,"X":1416882.561,"DTP":5094.9,"Dis":11363.8},{"No":2,"ZID":2,"IsIn":false,"Y":270172.377,"X":1416772.175,"DTP":641.6,"Dis":5524.6},{"No":3,"ZID":2,"IsIn":false,"Y":270128.147,"X":1416839.963,"DTP":327.9,"Dis":971.4},{"No":4,"ZID":2,"IsIn":false,"Y":270146.747,"X":1416816.37,"DTP":28.5,"Dis":360.5},{"No":5,"ZID":2,"IsIn":false,"Y":270140.109,"X":1416822.178,"DTP":74.6,"Dis":105.9},{"No":6,"ZID":2,"IsIn":false,"Y":270146.826,"X":1416816.817,"DTP":24.8,"Dis":103.1},{"No":7,"ZID":0,"IsIn":true,"Y":270145.328,"X":1416818.488,"DTP":0,"Dis":24.8}],"HPR":"3","Pos":"61","TPR":"18","ID":"48126"},{"HSc":"5","Sks":[{"No":1,"ZID":4,"IsIn":false,"Y":269622.849,"X":1416945.523,"DTP":6450.4,"Dis":10041.8},{"No":2,"ZID":1,"IsIn":false,"Y":269823.824,"X":1416900.082,"DTP":3980.8,"Dis":2474.8},{"No":3,"ZID":2,"IsIn":false,"Y":270125.279,"X":1416815.79,"DTP":240.8,"Dis":3758.6},{"No":4,"ZID":2,"IsIn":false,"Y":270147.619,"X":1416817.531,"DTP":27.7,"Dis":269.1},{"No":5,"ZID":0,"IsIn":true,"Y":270145.328,"X":1416818.488,"DTP":0,"Dis":27.7}],"HPR":"1","Pos":"T12","TPR":"8","ID":"33122"},{"HSc":"5","Sks":[{"No":1,"ZID":4,"IsIn":false,"Y":269678.132,"X":1416962.394,"DTP":5864.6,"Dis":10685.3},{"No":2,"ZID":2,"IsIn":false,"Y":270150.2,"X":1416800.285,"DTP":224.1,"Dis":5990.1},{"No":3,"ZID":2,"IsIn":false,"Y":270157.064,"X":1416819.608,"DTP":139.4,"Dis":246.1},{"No":4,"ZID":2,"IsIn":false,"Y":270146.272,"X":1416818.53,"DTP":9.2,"Dis":130.2},{"No":5,"ZID":0,"IsIn":true,"Y":270145.328,"X":1416818.488,"DTP":0,"Dis":9.2}],"HPR":"1","Pos":"T56","TPR":"17","ID":"55412"},{"HSc":"2","Sks":[{"No":1,"ZID":1,"IsIn":false,"Y":269730.877,"X":1416875.845,"DTP":5020.2,"Dis":11439.4},{"No":2,"ZID":0,"IsIn":true,"Y":270145.328,"X":1416818.488,"DTP":0,"Dis":5020.2}],"HPR":"-2","Pos":"T36","TPR":"13","ID":"27644"},{"HSc":"4","Sks":[{"No":1,"ZID":1,"IsIn":false,"Y":269667.387,"X":1416878.636,"DTP":5780.4,"Dis":10683.9},{"No":2,"ZID":2,"IsIn":false,"Y":270136.746,"X":1416824.205,"DTP":121.7,"Dis":5672.0},{"No":3,"ZID":2,"IsIn":false,"Y":270148.192,"X":1416816.211,"DTP":41.8,"Dis":167.6},{"No":4,"ZID":0,"IsIn":true,"Y":270145.328,"X":1416818.488,"DTP":0,"Dis":41.8}],"HPR":"0","Pos":"T41","TPR":"14","ID":"99160"},{"HSc":"4","Sks":[{"No":1,"ZID":1,"IsIn":false,"Y":269758.838,"X":1416900.03,"DTP":4739.6,"Dis":11728.4},{"No":2,"ZID":2,"IsIn":false,"Y":270190.017,"X":1416830.248,"DTP":552.5,"Dis":5243.3},{"No":3,"ZID":2,"IsIn":false,"Y":270144.658,"X":1416818.465,"DTP":5.9,"Dis":562.5},{"No":4,"ZID":0,"IsIn":true,"Y":270145.328,"X":1416818.488,"DTP":0,"Dis":5.9}],"HPR":"0","Pos":"T25","TPR":"12","ID":"25686"},{"HSc":"4","Sks":[{"No":1,"ZID":1,"IsIn":false,"Y":269804.912,"X":1416902.25,"DTP":4207.4,"Dis":12273.7},{"No":2,"ZID":1,"IsIn":false,"Y":269795.268,"X":1416898.759,"DTP":4310.1,"Dis":123.1},{"No":3,"ZID":2,"IsIn":false,"Y":270181.877,"X":1416820.66,"DTP":437.3,"Dis":4735.5},{"No":4,"ZID":2,"IsIn":false,"Y":270141.291,"X":1416820.246,"DTP":50.7,"Dis":487.1},{"No":5,"ZID":0,"IsIn":true,"Y":270145.328,"X":1416818.488,"DTP":0,"Dis":50.7}],"HPR":"0","Pos":"T56","TPR":"17","ID":"45609"},{"HSc":"4","Sks":[{"No":1,"ZID":1,"IsIn":false,"Y":269782.582,"X":1416851.985,"DTP":4370.2,"Dis":12098.3},{"No":2,"ZID":2,"IsIn":false,"Y":270155.141,"X":1416819.068,"DTP":115.9,"Dis":4489.0},{"No":3,"ZID":2,"IsIn":false,"Y":270142.588,"X":1416818.507,"DTP":30.8,"Dis":150.8},{"No":4,"ZID":0,"IsIn":true,"Y":270145.328,"X":1416818.488,"DTP":0,"Dis":30.8}],"HPR":"0","Pos":"T36","TPR":"13","ID":"24361"},{"HSc":"4","Sks":[{"No":1,"ZID":1,"IsIn":false,"Y":269744.79,"X":1416870.501,"DTP":4846.0,"Dis":11614.3},{"No":2,"ZID":2,"IsIn":false,"Y":270161.962,"X":1416826.147,"DTP":217.7,"Dis":5035.6},{"No":3,"ZID":2,"IsIn":false,"Y":270143.867,"X":1416816.917,"DTP":23.6,"Dis":243.8},{"No":4,"ZID":0,"IsIn":true,"Y":270145.328,"X":1416818.488,"DTP":0,"Dis":23.6}],"HPR":"0","Pos":"T25","TPR":"12","ID":"33448"},{"HSc":"4","Sks":[{"No":1,"ZID":1,"IsIn":false,"Y":269709.694,"X":1416884.548,"DTP":5287.0,"Dis":11172.3},{"No":2,"ZID":2,"IsIn":false,"Y":270171.113,"X":1416828.622,"DTP":330.4,"Dis":5579.3},{"No":3,"ZID":2,"IsIn":false,"Y":270145.152,"X":1416817.803,"DTP":6.4,"Dis":337.6},{"No":4,"ZID":0,"IsIn":true,"Y":270145.328,"X":1416818.488,"DTP":0,"Dis":6.4}],"HPR":"0","Pos":"T48","TPR":"16","ID":"10809"},{"HSc":"5","Sks":[{"No":1,"ZID":1,"IsIn":false,"Y":269668.977,"X":1416873.286,"DTP":5753.9,"Dis":10713.8},{"No":2,"ZID":1,"IsIn":false,"Y":270111.35,"X":1416819.127,"DTP":406.4,"Dis":5349.7},{"No":3,"ZID":2,"IsIn":false,"Y":270152.115,"X":1416819.658,"DTP":80.6,"Dis":489.9},{"No":4,"ZID":2,"IsIn":false,"Y":270140.358,"X":1416818.182,"DTP":57.7,"Dis":142.2},{"No":5,"ZID":0,"IsIn":true,"Y":270145.328,"X":1416818.488,"DTP":0,"Dis":57.7}],"HPR":"1","Pos":"T25","TPR":"12","ID":"27349"},{"HSc":"4","Sks":[{"No":1,"ZID":20,"IsIn":false,"Y":269729.108,"X":1416907.031,"DTP":5105.7,"Dis":11363.6},{"No":2,"ZID":1,"IsIn":false,"Y":270108.632,"X":1416816.864,"DTP":439.4,"Dis":4682.0},{"No":3,"ZID":2,"IsIn":false,"Y":270150.113,"X":1416815.124,"DTP":68.1,"Dis":498.9},{"No":4,"ZID":0,"IsIn":true,"Y":270145.328,"X":1416818.488,"DTP":0,"Dis":68.1}],"HPR":"0","Pos":"T25","TPR":"12","ID":"21961"},{"HSc":"3","Sks":[{"No":1,"ZID":1,"IsIn":false,"Y":269754.85,"X":1416865.227,"DTP":4718.2,"Dis":11743.6},{"No":2,"ZID":2,"IsIn":false,"Y":270139.318,"X":1416806.916,"DTP":154.4,"Dis":4667.5},{"No":3,"ZID":0,"IsIn":true,"Y":270145.328,"X":1416818.488,"DTP":0,"Dis":154.4}],"HPR":"-1","Pos":"T36","TPR":"13","ID":"26499"},{"HSc":"4","Sks":[{"No":1,"ZID":19,"IsIn":false,"Y":269627.445,"X":1416989.325,"DTP":6542.2,"Dis":10058.0},{"No":2,"ZID":1,"IsIn":false,"Y":270225.434,"X":1416803.073,"DTP":976.8,"Dis":7516.2},{"No":3,"ZID":2,"IsIn":false,"Y":270142.74,"X":1416822.999,"DTP":60.3,"Dis":1020.7},{"No":4,"ZID":0,"IsIn":true,"Y":270145.328,"X":1416818.488,"DTP":0,"Dis":60.3}],"HPR":"0","Pos":"T45","TPR":"15","ID":"26851"},{"HSc":"4","Sks":[{"No":1,"ZID":1,"IsIn":false,"Y":269750.953,"X":1416849.676,"DTP":4746.3,"Dis":11730.5},{"No":2,"ZID":2,"IsIn":false,"Y":270124.981,"X":1416826.896,"DTP":262.3,"Dis":4497.6},{"No":3,"ZID":2,"IsIn":false,"Y":270148.059,"X":1416816.887,"DTP":35.9,"Dis":302.0},{"No":4,"ZID":0,"IsIn":true,"Y":270145.328,"X":1416818.488,"DTP":0,"Dis":35.9}],"HPR":"0","Pos":"T12","TPR":"8","ID":"40098"},{"HSc":"4","Sks":[{"No":1,"ZID":1,"IsIn":false,"Y":269687.921,"X":1416875.671,"DTP":5531.5,"Dis":10932.5},{"No":2,"ZID":2,"IsIn":false,"Y":270134.111,"X":1416841.264,"DTP":302.6,"Dis":5372.2},{"No":3,"ZID":2,"IsIn":false,"Y":270146.719,"X":1416815.28,"DTP":39.9,"Dis":346.6},{"No":4,"ZID":0,"IsIn":true,"Y":270145.328,"X":1416818.488,"DTP":0,"Dis":39.9}],"HPR":"0","Pos":"T20","TPR":"11","ID":"32102"},{"HSc":"3","Sks":[{"No":1,"ZID":1,"IsIn":false,"Y":269648.147,"X":1416871.402,"DTP":5999.7,"Dis":10472.0},{"No":2,"ZID":2,"IsIn":false,"Y":270161.485,"X":1416829.578,"DTP":233.1,"Dis":6182.4},{"No":3,"ZID":0,"IsIn":true,"Y":270145.328,"X":1416818.488,"DTP":0,"Dis":233.1}],"HPR":"-1","Pos":"T25","TPR":"12","ID":"34098"},{"HSc":"3","Sks":[{"No":1,"ZID":1,"IsIn":false,"Y":269755.277,"X":1416873.348,"DTP":4725.8,"Dis":11732.7},{"No":2,"ZID":2,"IsIn":false,"Y":270149.514,"X":1416826.395,"DTP":105.3,"Dis":4765.5},{"No":3,"ZID":0,"IsIn":true,"Y":270145.328,"X":1416818.488,"DTP":0,"Dis":105.3}],"HPR":"-1","Pos":"T25","TPR":"12","ID":"24138"},{"HSc":"5","Sks":[{"No":1,"ZID":4,"IsIn":false,"Y":269609.861,"X":1416942.532,"DTP":6593.8,"Dis":9890.5},{"No":2,"ZID":20,"IsIn":false,"Y":270233.941,"X":1416776.82,"DTP":1173.0,"Dis":7748.6},{"No":3,"ZID":2,"IsIn":false,"Y":270143.251,"X":1416828.727,"DTP":123.3,"Dis":1254.0},{"No":4,"ZID":2,"IsIn":false,"Y":270146.201,"X":1416816.771,"DTP":21.0,"Dis":147.8},{"No":5,"ZID":0,"IsIn":true,"Y":270145.328,"X":1416818.488,"DTP":0,"Dis":21.0}],"HPR":"1","Pos":"1","TPR":"1","ID":"36689"},{"HSc":"4","Sks":[{"No":1,"ZID":1,"IsIn":false,"Y":269713.385,"X":1416873.906,"DTP":5225.4,"Dis":11236.7},{"No":2,"ZID":2,"IsIn":false,"Y":270135.812,"X":1416821.443,"DTP":117.5,"Dis":5109.8},{"No":3,"ZID":2,"IsIn":false,"Y":270148.775,"X":1416817.298,"DTP":41.7,"Dis":163.4},{"No":4,"ZID":0,"IsIn":true,"Y":270145.328,"X":1416818.488,"DTP":0,"Dis":41.7}],"HPR":"0","Pos":"T6","TPR":"6","ID":"21528"},{"HSc":"4","Sks":[{"No":1,"ZID":1,"IsIn":false,"Y":269704.781,"X":1416876.68,"DTP":5332.2,"Dis":11129.5},{"No":2,"ZID":2,"IsIn":false,"Y":270139.992,"X":1416827.116,"DTP":119.6,"Dis":5258.1},{"No":3,"ZID":2,"IsIn":false,"Y":270145.897,"X":1416816.039,"DTP":28.1,"Dis":150.6},{"No":4,"ZID":0,"IsIn":true,"Y":270145.328,"X":1416818.488,"DTP":0,"Dis":28.1}],"HPR":"0","Pos":"T10","TPR":"7","ID":"22405"},{"HSc":"4","Sks":[{"No":1,"ZID":1,"IsIn":false,"Y":269676.567,"X":1416873.223,"DTP":5663.3,"Dis":10803.5},{"No":2,"ZID":2,"IsIn":false,"Y":270139.225,"X":1416833.927,"DTP":197.1,"Dis":5574.0},{"No":3,"ZID":2,"IsIn":false,"Y":270147.467,"X":1416816.54,"DTP":32.6,"Dis":230.9},{"No":4,"ZID":0,"IsIn":true,"Y":270145.328,"X":1416818.488,"DTP":0,"Dis":32.6}],"HPR":"0","Pos":"T20","TPR":"11","ID":"12716"},{"HSc":"4","Sks":[{"No":1,"ZID":4,"IsIn":false,"Y":269654.417,"X":1416927.592,"DTP":6033.3,"Dis":10443.3},{"No":2,"ZID":19,"IsIn":false,"Y":269880.118,"X":1416757.28,"DTP":3265.0,"Dis":3393.0},{"No":3,"ZID":2,"IsIn":false,"Y":270170.217,"X":1416824.856,"DTP":306.3,"Dis":3575.1},{"No":4,"ZID":0,"IsIn":true,"Y":270145.328,"X":1416818.488,"DTP":0,"Dis":306.3}],"HPR":"0","Pos":"2","TPR":"2","ID":"30911"},{"HSc":"4","Sks":[{"No":1,"ZID":3,"IsIn":false,"Y":269561.393,"X":1416944.003,"DTP":7165.7,"Dis":9312.2},{"No":2,"ZID":1,"IsIn":false,"Y":269994.585,"X":1416844.803,"DTP":1834.8,"Dis":5333.0},{"No":3,"ZID":2,"IsIn":false,"Y":270140.947,"X":1416818.023,"DTP":50.8,"Dis":1786.1},{"No":4,"ZID":0,"IsIn":true,"Y":270145.328,"X":1416818.488,"DTP":0,"Dis":50.8}],"HPR":"0","Pos":"T45","TPR":"15","ID":"25818"},{"HSc":"4","Sks":[{"No":1,"ZID":1,"IsIn":false,"Y":269656.268,"X":1416873.134,"DTP":5905.1,"Dis":10564.1},{"No":2,"ZID":2,"IsIn":false,"Y":270141.93,"X":1416829.341,"DTP":134.4,"Dis":5853.6},{"No":3,"ZID":2,"IsIn":false,"Y":270145.5,"X":1416815.395,"DTP":35.1,"Dis":172.7},{"No":4,"ZID":0,"IsIn":true,"Y":270145.328,"X":1416818.488,"DTP":0,"Dis":35.1}],"HPR":"0","Pos":"3","TPR":"3","ID":"30925"}],"Te":{"Y":268790.58,"X":1417030.33},"Eag":1,"DBg":3,"Prs":42,"Fg":{"Y":270145.328,"X":1416818.488},"Avg":"4.060","Bir":11,"ID":12,"Bog":10}],"ID":3}]}